Workbook

Sheet Read me
A1: 351 Impact Scoring — v1 (28 Oct 2026)
A3: What this is: every 351 success story and record-based outcome, scored the Founders Pledge way.
A4: Impact points (Founder Steps) = Outcome weight × Evidence weight × 351 share. Method doc: "351 Impact Method" (Claude Docs).
A6: HOW TO USE
A7: 1. Yellow cells are inputs. Everything else is a formula — do not type over it.
A8: 2. Weights tab: change any weight and every score updates.
A9: 3. Stories tab: add new stories at the bottom (copy the formulas in columns N–R from the row above). Fill column L when a survey answer arrives.
A10: 4. Costs & multiplier tab: fill the yellow costs and values — € per Founder Step and the multiplier appear on their own.
A11: 5. Summary tab: the numbers for funders.
A13: EXAMPLE ROW (Stories tab format)
A14: ID: ST99 · Year: 2026 · Who: Founder of Acme (example) · Initiative: Startup Weekend Porto · What changed: Raised €150k pre-seed · Code: S3 · Stage: Company Creation · Core team: N · Grade: B · Evidence: her LinkedIn post · Role: Contributing · Survey: Probably not
A16: OUTCOME CODES
... A23: Records: 351_PRR_5196_Evidencias.xlsx (PRR Impact folder), tabs Resumo, Startups constituídas, Continuidade do apoio; read 28 Oct 2026.

Sheet Summary
A1: 351 impact — summary
A3: Code | B3: Outcome | C3: Stories counted | D3: From records | E3: Total outcomes | F3: Impact points (Founder Steps) | G3: Share of points
A4: S1 | B4: Startup created / idea validated | C4: =COUNTIFS(Stories!$F$2:$F$500,A4,Stories!$N$2:$N$500,1) -> 0 | D4: =SUMIFS(Records!$D$2:$D$6,Records!$B$2:$B$6,A4) -> 47 | E4: =C4+D4 -> 47 | F4: =SUMIFS(Stories!$R$2:$R$500,Stories!$F$2:$F$500,A4)+SUMIFS(Records!$K$2:$K$6,Records!$B$2:$B$6,A4) -> 23.5 | G4: =IF($F$14=0,0,F4/$F$14) -> 0.34740188
A5: S2 | B5: Startup moved to next programme (incubator, accelerator) | C5: =COUNTIFS(Stories!$F$2:$F$500,A5,Stories!$N$2:$N$500,1) -> 6 | D5: =SUMIFS(Records!$D$2:$D$6,Records!$B$2:$B$6,A5) -> 0 | E5: =C5+D5 -> 6 | F5: =SUMIFS(Stories!$R$2:$R$500,Stories!$F$2:$F$500,A5)+SUMIFS(Records!$K$2:$K$6,Records!$B$2:$B$6,A5) -> 4.75 | G5: =IF($F$14=0,0,F5/$F$14) -> 0.070219528
A6: S3 | B6: Traction: launch, pilot, revenue, funding | C6: =COUNTIFS(Stories!$F$2:$F$500,A6,Stories!$N$2:$N$500,1) -> 4 | D6: =SUMIFS(Records!$D$2:$D$6,Records!$B$2:$B$6,A6) -> 0 | E6: =C6+D6 -> 4 | F6: =SUMIFS(Stories!$R$2:$R$500,Stories!$F$2:$F$500,A6)+SUMIFS(Records!$K$2:$K$6,Records!$B$2:$B$6,A6) -> 3.375 | G6: =IF($F$14=0,0,F6/$F$14) -> 0.049892823
A7: S4 | B7: Award or shortlist | C7: =COUNTIFS(Stories!$F$2:$F$500,A7,Stories!$N$2:$N$500,1) -> 6 | D7: =SUMIFS(Records!$D$2:$D$6,Records!$B$2:$B$6,A7) -> 0 | E7: =C7+D7 -> 6 | F7: =SUMIFS(Stories!$R$2:$R$500,Stories!$F$2:$F$500,A7)+SUMIFS(Records!$K$2:$K$6,Records!$B$2:$B$6,A7) -> 3.95 | G7: =IF($F$14=0,0,F7/$F$14) -> 0.058393082
A8: J | B8: Job or career move through 351 | C8: =COUNTIFS(Stories!$F$2:$F$500,A8,Stories!$N$2:$N$500,1) -> 11 | D8: =SUMIFS(Records!$D$2:$D$6,Records!$B$2:$B$6,A8) -> 0 | E8: =C8+D8 -> 11 | F8: =SUMIFS(Stories!$R$2:$R$500,Stories!$F$2:$F$500,A8)+SUMIFS(Records!$K$2:$K$6,Records!$B$2:$B$6,A8) -> 4 | G8: =IF($F$14=0,0,F8/$F$14) -> 0.059132234
A9: N | B9: Partner, co-founder, client or hire found through 351 | C9: =COUNTIFS(Stories!$F$2:$F$500,A9,Stories!$N$2:$N$500,1) -> 8 | D9: =SUMIFS(Records!$D$2:$D$6,Records!$B$2:$B$6,A9) -> 0 | E9: =C9+D9 -> 8 | F9: =SUMIFS(Stories!$R$2:$R$500,Stories!$F$2:$F$500,A9)+SUMIFS(Records!$K$2:$K$6,Records!$B$2:$B$6,A9) -> 2.5875 | G9: =IF($F$14=0,0,F9/$F$14) -> 0.038251164
A10: L | B10: New community leader or initiative | C10: =COUNTIFS(Stories!$F$2:$F$500,A10,Stories!$N$2:$N$500,1) -> 7 | D10: =SUMIFS(Records!$D$2:$D$6,Records!$B$2:$B$6,A10) -> 5 | E10: =C10+D10 -> 12 | F10: =SUMIFS(Stories!$R$2:$R$500,Stories!$F$2:$F$500,A10)+SUMIFS(Records!$K$2:$K$6,Records!$B$2:$B$6,A10) -> 5.8 | G10: =IF($F$14=0,0,F10/$F$14) -> 0.08574174
A11: C | B11: Continued in another 351 programme | C11: =COUNTIFS(Stories!$F$2:$F$500,A11,Stories!$N$2:$N$500,1) -> 0 | D11: =SUMIFS(Records!$D$2:$D$6,Records!$B$2:$B$6,A11) -> 73 | E11: =C11+D11 -> 73 | F11: =SUMIFS(Stories!$R$2:$R$500,Stories!$F$2:$F$500,A11)+SUMIFS(Records!$K$2:$K$6,Records!$B$2:$B$6,A11) -> 18.25 | G11: =IF($F$14=0,0,F11/$F$14) -> 0.26979082
A12: V | B12: Felt value / learning (testimonial) | C12: =COUNTIFS(Stories!$F$2:$F$500,A12,Stories!$N$2:$N$500,1) -> 16 | D12: =SUMIFS(Records!$D$2:$D$6,Records!$B$2:$B$6,A12) -> 0 | E12: =C12+D12 -> 16 | F12: =SUMIFS(Stories!$R$2:$R$500,Stories!$F$2:$F$500,A12)+SUMIFS(Records!$K$2:$K$6,Records!$B$2:$B$6,A12) -> 1.3125 | G12: =IF($F$14=0,0,F12/$F$14) -> 0.019402764
A13: R | B13: Recognition of a community member | C13: =COUNTIFS(Stories!$F$2:$F$500,A13,Stories!$N$2:$N$500,1) -> 3 | D13: =SUMIFS(Records!$D$2:$D$6,Records!$B$2:$B$6,A13) -> 0 | E13: =C13+D13 -> 3 | F13: =SUMIFS(Stories!$R$2:$R$500,Stories!$F$2:$F$500,A13)+SUMIFS(Records!$K$2:$K$6,Records!$B$2:$B$6,A13) -> 0.12 | G13: =IF($F$14=0,0,F13/$F$14) -> 0.001773967
A14: Total | C14: =SUM(C4:C13) -> 61 | D14: =SUM(D4:D13) -> 125 | E14: =SUM(E4:E13) -> 186 | F14: =SUM(F4:F13) -> 67.645 | G14: =IF($F$14=0,0,F14/$F$14) -> 1
A16: Evidence quality of counted stories
A17: Grade | B17: Stories | C17: Share
A18: A | B18: =COUNTIFS(Stories!$I$2:$I$500,A18,Stories!$N$2:$N$500,1) -> 10 | C18: =IF(SUM($B$18:$B$20)=0,0,B18/SUM($B$18:$B$20)) -> 0.16393443
A19: B | B19: =COUNTIFS(Stories!$I$2:$I$500,A19,Stories!$N$2:$N$500,1) -> 22 | C19: =IF(SUM($B$18:$B$20)=0,0,B19/SUM($B$18:$B$20)) -> 0.36065574
A20: C | B20: =COUNTIFS(Stories!$I$2:$I$500,A20,Stories!$N$2:$N$500,1) -> 29 | C20: =IF(SUM($B$18:$B$20)=0,0,B20/SUM($B$18:$B$20)) -> 0.47540984
A22: Other checks
A23: Story rows in total | C23: =COUNTA(Stories!$A$2:$A$500) -> 87
A24: Rows not counted: team credibility (X) | C24: =COUNTIF(Stories!$F$2:$F$500,"X") -> 10
A25: Rows not counted: benefit given (O) | C25: =COUNTIF(Stories!$F$2:$F$500,"O") -> 4
A26: Rows not counted: needs info (Q) | C26: =COUNTIF(Stories!$F$2:$F$500,"Q") -> 2
A27: Rows not counted: duplicate of another row | C27: =COUNTIFS(Stories!$M$2:$M$500,"<>",Stories!$F$2:$F$500,"<>X",Stories!$F$2:$F$500,"<>O",Stories!$F$2:$F$500,"<>Q") -> 10
A28: Story rows counted | C28: =SUM(Stories!$N$2:$N$500) -> 61
A29: Counted stories about the core team | C29: =COUNTIFS(Stories!$H$2:$H$500,"Y",Stories!$N$2:$N$500,1) -> 3
A30: Survey answers received | C30: =COUNTA(Stories!$L$2:$L$500) -> 0
A31: Extra points if every C story got a quote (C → B) | C31: =SUMPRODUCT((Stories!$I$2:$I$500="C")*Stories!$R$2:$R$500)*(Weights!$B$22/Weights!$B$23-1) -> 6.015

Sheet Costs & multiplier
A1: Costs, € per Founder Step and the €1 → €X multiplier
A2: Fill the yellow cells for the SAME period as the stories (suggested: 1 Jan 2025 – 31 Dec 2025). Leave blank what you do not know — results show "—".
A4: 351 cash costs (€) | B4: Amount (€) | C4: Source / note
A5: Techstars Startup Weekends
A6: Coworking Thursdays
A7: Portugal Tech Week
A8: Community Leaders Academy
A9: Startuppers + Startup Clinics
A10: Founder Institute Portugal
A11: Community (Slack, newsletter, tools)
A12: Paid staff and admin
A13: Other
A14: Total 351 cash cost | B14: =SUM(B5:B13) -> 0
A16: Value 351 unlocked (€) | B16: Amount | C16: Source / note
A17: Volunteer hours (number) | C17: Count: volunteers × hours per month × months
A18: Value of one volunteer hour (€) | C18: Use a public reference (e.g. average hourly wage in Portugal, INE) and cite it
A19: Volunteer time value | B19: =B17*B18 -> 0
A20: Partner in-kind (venues, catering, mentors, perks actually used) | C20: Perks: count credits USED, not the "€700k available" headline
A21: Partner cash into 351 programmes (sponsors)
A22: Capital raised by alumni startups | C22: Only rounds with a public source
A23: 351 share of alumni capital | B23: 0.25 | C23: Same idea as the 351 share on stories (default = Contributing 0.25)
A24: Alumni capital credited to 351 | B24: =B22*B23 -> 0
A25: Total value unlocked | B25: =B19+B20+B21+B24 -> 0
A27: Results | B27: Value | C27: How it is read
A28: Impact points (Founder Steps), from Summary | B28: =Summary!F14 -> 67.645
A29: € per Founder Step | B29: =IF(OR(B14=0,B28=0),"—",B14/B28) -> — | C29: What it costs 351 to move one founder one real step
A30: Multiplier: every €1 to 351 unlocks | B30: =IF(OR(B14=0,B25=0),"—",B25/B14) -> — | C30: Like Founders Pledge "$1 → $31.10 moved"
A31: Next €50k buys about (Founder Steps) | B31: =IF(OR(B14=0,B28=0),"—",50000/B29) -> — | C31: Average-cost estimate; refine per programme (see method doc, "What the next €50k buys")

Sheet Weights
A1: Weights (edit the yellow cells)
A3: Outcome weights — Founder Steps
A4: Code | B4: Weight | C4: Outcome | D4: Counted?
A5: S1 | B5: 1 | C5: Startup created / idea validated | D5: Yes
A6: S2 | B6: 2 | C6: Startup moved to next programme (incubator, accelerator) | D6: Yes
A7: S3 | B7: 3 | C7: Traction: launch, pilot, revenue, funding | D7: Yes
A8: S4 | B8: 2 | C8: Award or shortlist | D8: Yes
A9: J | B9: 2 | C9: Job or career move through 351 | D9: Yes
A10: N | B10: 1.5 | C10: Partner, co-founder, client or hire found through 351 | D10: Yes
A11: L | B11: 2 | C11: New community leader or initiative | D11: Yes
A12: C | B12: 0.5 | C12: Continued in another 351 programme | D12: Yes
A13: V | B13: 0.25 | C13: Felt value / learning (testimonial) | D13: Yes, low weight
A14: R | B14: 0.5 | C14: Recognition of a community member | D14: Yes, low weight
A15: X | B15: 0 | C15: Team award / credibility | D15: No
A16: O | B16: 0 | C16: Benefit given (ticket, perk) | D16: No
A17: Q | B17: 0 | C17: Needs info | D17: No
A19: Evidence weights (confidence discount)
A20: Grade | B20: Weight | C20: Meaning
A21: A | B21: 1 | C21: 351 records with names, or an independent page (press, official site)
A22: B | B22: 0.7 | C22: The person's own public post or written message
A23: C | B23: 0.4 | C23: Told by the team, no link or record
A25: 351 share before a survey answer (from 351's role)
A26: Role | B26: Share | C26: Meaning
A27: Direct | B27: 0.5 | C27: The 351 programme or referral was the key step
A28: Contributing | B28: 0.25 | C28: One of several inputs
A29: Unclear | B29: 0.1 | C29: Role not known
A31: 351 share from the survey: 'Would this have happened without 351?'
A32: Answer | B32: Share | C32: Why
A33: No, definitely not | B33: 0.8 | C33: Capped below 1.0: people credit whoever asks
A34: Probably not | B34: 0.6
A35: Yes, but later or smaller | B35: 0.3
A36: Yes, the same anyway | B36: 0 | C36: No credit to 351
A38: Weights are a judgement call (ours, 28 Oct 2026), modelled on Founders Pledge confidence discounts. Change them and every score updates.

Sheet Stories
A1: ID | B1: Year | C1: Who | D1: Initiative | E1: What changed | F1: Outcome code | G1: Funnel stage | H1: Core team? | I1: Evidence grade | J1: Evidence / source | K1: 351 role | L1: Survey answer (input) | M1: Duplicate of | N1: Counted? (1/0) | O1: Outcome weight | P1: Evidence weight | Q1: 351 share | R1: Impact points (Founder Steps) | S1: Next action
A2: ST01 | B2: 2026 | C2: Member (351 Slack) | D2: 351 Slack | E2: Found a web designer, content manager, video editor, Meta Ads buyer and a client through 351 Slack in 12 months | F2: N | G2: Community Building | H2: N | I2: B | J2: Own Slack post (screenshot in Drive) | K2: Direct | N2: =IF(OR(M2<>"",F2="X",F2="O",F2="Q"),0,1) -> 1 | O2: =IFERROR(INDEX(Weights!$B$5:$B$17,MATCH(F2,Weights!$A$5:$A$17,0)),0) -> 1.5 | P2: =IFERROR(INDEX(Weights!$B$21:$B$23,MATCH(I2,Weights!$A$21:$A$23,0)),0) -> 0.7 | Q2: =IF(L2<>"",IFERROR(INDEX(Weights!$B$33:$B$36,MATCH(L2,Weights!$A$33:$A$36,0)),0),IFERROR(INDEX(Weights!$B$27:$B$29,MATCH(K2,Weights!$A$27:$A$29,0)),0)) -> 0.5 | R2: =N2*O2*P2*Q2 -> 0.525 | S2: Ask for count of hires and client value
A3: ST02 | B3: 2026 | C3: Founders of Menostart (SW Coimbra) | D3: Startup Weekend Coimbra | E3: Building Menostart, a menopause health platform; featured by Coimbra Coolectiva | F3: S1 | G3: Ideation | H3: N | I3: A | J3: Press: coimbracoolectiva.pt + LinkedIn; in PRR startups list | K3: Direct | M3: REC-S1 | N3: =IF(OR(M3<>"",F3="X",F3="O",F3="Q"),0,1) -> 0 | O3: =IFERROR(INDEX(Weights!$B$5:$B$17,MATCH(F3,Weights!$A$5:$A$17,0)),0) -> 1 | P3: =IFERROR(INDEX(Weights!$B$21:$B$23,MATCH(I3,Weights!$A$21:$A$23,0)),0) -> 1 | Q3: =IF(L3<>"",IFERROR(INDEX(Weights!$B$33:$B$36,MATCH(L3,Weights!$A$33:$A$36,0)),0),IFERROR(INDEX(Weights!$B$27:$B$29,MATCH(K3,Weights!$A$27:$A$29,0)),0)) -> 0.5 | R3: =N3*O3*P3*Q3 -> 0 | S3: Counted in records; keep as illustration
A4: ST03 | B4: 2026 | C4: Founder of Lunia (Tech Days Viana) | D4: Tech Days Viana do Castelo | E4: 2025 pitch winner Lunia has a prototype online and is raising a €300k pre-seed | F4: S3 | G4: Company Creation | H4: N | I4: A | J4: Press: Portugal Startup News, 7 Jun 2026 | K4: Contributing | N4: =IF(OR(M4<>"",F4="X",F4="O",F4="Q"),0,1) -> 1 | O4: =IFERROR(INDEX(Weights!$B$5:$B$17,MATCH(F4,Weights!$A$5:$A$17,0)),0) -> 3 | P4: =IFERROR(INDEX(Weights!$B$21:$B$23,MATCH(I4,Weights!$A$21:$A$23,0)),0) -> 1 | Q4: =IF(L4<>"",IFERROR(INDEX(Weights!$B$33:$B$36,MATCH(L4,Weights!$A$33:$A$36,0)),0),IFERROR(INDEX(Weights!$B$27:$B$29,MATCH(K4,Weights!$A$27:$A$29,0)),0)) -> 0.25 | R4: =N4*O4*P4*Q4 -> 0.75 | S4: Ask if round closed and amount
A5: ST04 | C5: Coworking host | D5: Coworking Thursdays, CLA | E5: Hosted CT, was introduced to Unicorn Factory, now runs a hub with them; now sponsors 351 | F5: N | G5: Ecosystem Enablement | H5: N | I5: C | J5: Team account | K5: Direct | N5: =IF(OR(M5<>"",F5="X",F5="O",F5="Q"),0,1) -> 1 | O5: =IFERROR(INDEX(Weights!$B$5:$B$17,MATCH(F5,Weights!$A$5:$A$17,0)),0) -> 1.5 | P5: =IFERROR(INDEX(Weights!$B$21:$B$23,MATCH(I5,Weights!$A$21:$A$23,0)),0) -> 0.4 | Q5: =IF(L5<>"",IFERROR(INDEX(Weights!$B$33:$B$36,MATCH(L5,Weights!$A$33:$A$36,0)),0),IFERROR(INDEX(Weights!$B$27:$B$29,MATCH(K5,Weights!$A$27:$A$29,0)),0)) -> 0.5 | R5: =N5*O5*P5*Q5 -> 0.3 | S5: Get a quote + hub name/date
A6: ST05 | C6: Two Coworking Thursdays members | D6: Coworking Thursdays | E6: Met at CT and became business partners | F6: N | G6: Community Building | H6: N | I6: C | J6: Team account | K6: Direct | N6: =IF(OR(M6<>"",F6="X",F6="O",F6="Q"),0,1) -> 1 | O6: =IFERROR(INDEX(Weights!$B$5:$B$17,MATCH(F6,Weights!$A$5:$A$17,0)),0) -> 1.5 | P6: =IFERROR(INDEX(Weights!$B$21:$B$23,MATCH(I6,Weights!$A$21:$A$23,0)),0) -> 0.4 | Q6: =IF(L6<>"",IFERROR(INDEX(Weights!$B$33:$B$36,MATCH(L6,Weights!$A$33:$A$36,0)),0),IFERROR(INDEX(Weights!$B$27:$B$29,MATCH(K6,Weights!$A$27:$A$29,0)),0)) -> 0.5 | R6: =N6*O6*P6*Q6 -> 0.3 | S6: Get a quote or LinkedIn post
A7: ST06 | C7: Founder team (Coworking Thursdays regulars) | D7: Coworking Thursdays → Startup Weekend | E7: Years at CT, then 3rd place at a Startup Weekend; building MVP for a Dubai competition | F7: S1 | G7: Ideation | H7: N | I7: B | J7: LinkedIn post (founder) | K7: Direct | M7: REC-S1 | N7: =IF(OR(M7<>"",F7="X",F7="O",F7="Q"),0,1) -> 0 | O7: =IFERROR(INDEX(Weights!$B$5:$B$17,MATCH(F7,Weights!$A$5:$A$17,0)),0) -> 1 | P7: =IFERROR(INDEX(Weights!$B$21:$B$23,MATCH(I7,Weights!$A$21:$A$23,0)),0) -> 0.7 | Q7: =IF(L7<>"",IFERROR(INDEX(Weights!$B$33:$B$36,MATCH(L7,Weights!$A$33:$A$36,0)),0),IFERROR(INDEX(Weights!$B$27:$B$29,MATCH(K7,Weights!$A$27:$A$29,0)),0)) -> 0.5 | R7: =N7*O7*P7*Q7 -> 0 | S7: Check the startup is in the REC-S1 list; ask current stage
A8: ST07 | C8: Two Critical Software employees | D8: Startup Weekend Porto | E8: Critical Software staff won SW Porto, became internal role models, pitched at Elevador Santa Luzia | F8: S4 | G8: Ideation | H8: N | I8: C | J8: Team account; Critical use case in 351 pitch deck | K8: Direct | N8: =IF(OR(M8<>"",F8="X",F8="O",F8="Q"),0,1) -> 1 | O8: =IFERROR(INDEX(Weights!$B$5:$B$17,MATCH(F8,Weights!$A$5:$A$17,0)),0) -> 2 | P8: =IFERROR(INDEX(Weights!$B$21:$B$23,MATCH(I8,Weights!$A$21:$A$23,0)),0) -> 0.4 | Q8: =IF(L8<>"",IFERROR(INDEX(Weights!$B$33:$B$36,MATCH(L8,Weights!$A$33:$A$36,0)),0),IFERROR(INDEX(Weights!$B$27:$B$29,MATCH(K8,Weights!$A$27:$A$29,0)),0)) -> 0.5 | R8: =N8*O8*P8*Q8 -> 0.4 | S8: Get Critical's confirmation
A9: ST08 | C9: Workshop volunteer | D9: Workshops → Startup Weekend Lisbon | E9: Workshop volunteer joined SW Lisbon last minute, won 1st place, now building the business | F9: S1 | G9: Ideation | H9: N | I9: C | J9: Team account | K9: Direct | M9: REC-S1 | N9: =IF(OR(M9<>"",F9="X",F9="O",F9="Q"),0,1) -> 0 | O9: =IFERROR(INDEX(Weights!$B$5:$B$17,MATCH(F9,Weights!$A$5:$A$17,0)),0) -> 1 | P9: =IFERROR(INDEX(Weights!$B$21:$B$23,MATCH(I9,Weights!$A$21:$A$23,0)),0) -> 0.4 | Q9: =IF(L9<>"",IFERROR(INDEX(Weights!$B$33:$B$36,MATCH(L9,Weights!$A$33:$A$36,0)),0),IFERROR(INDEX(Weights!$B$27:$B$29,MATCH(K9,Weights!$A$27:$A$29,0)),0)) -> 0.5 | R9: =N9*O9*P9*Q9 -> 0 | S9: Check it is in REC-S1 (SW Lisboa 2024); get stage
A10: ST09 | C10: Weekend participant, now volunteer lead | D10: Startup Weekend Porto | E10: Joined SW Porto, became a volunteer lead: CT Porto, manages volunteers, taking SW to Braga | F10: L | G10: Ecosystem Enablement | H10: N | I10: C | J10: Team account | K10: Direct | N10: =IF(OR(M10<>"",F10="X",F10="O",F10="Q"),0,1) -> 1 | O10: =IFERROR(INDEX(Weights!$B$5:$B$17,MATCH(F10,Weights!$A$5:$A$17,0)),0) -> 2 | P10: =IFERROR(INDEX(Weights!$B$21:$B$23,MATCH(I10,Weights!$A$21:$A$23,0)),0) -> 0.4 | Q10: =IF(L10<>"",IFERROR(INDEX(Weights!$B$33:$B$36,MATCH(L10,Weights!$A$33:$A$36,0)),0),IFERROR(INDEX(Weights!$B$27:$B$29,MATCH(K10,Weights!$A$27:$A$29,0)),0)) -> 0.5 | R10: =N10*O10*P10*Q10 -> 0.4 | S10: Count events led
A11: ST10 | C11: Weekend participant | D11: Startup Weekend Lisbon | E11: After SW Lisbon, helps build membership + Startup School; their startup continued in Startuppers | F11: L | G11: Ecosystem Enablement | H11: N | I11: A | J11: PRR evidence file (Continuidade do apoio) | K11: Direct | N11: =IF(OR(M11<>"",F11="X",F11="O",F11="Q"),0,1) -> 1 | O11: =IFERROR(INDEX(Weights!$B$5:$B$17,MATCH(F11,Weights!$A$5:$A$17,0)),0) -> 2 | P11: =IFERROR(INDEX(Weights!$B$21:$B$23,MATCH(I11,Weights!$A$21:$A$23,0)),0) -> 1 | Q11: =IF(L11<>"",IFERROR(INDEX(Weights!$B$33:$B$36,MATCH(L11,Weights!$A$33:$A$36,0)),0),IFERROR(INDEX(Weights!$B$27:$B$29,MATCH(K11,Weights!$A$27:$A$29,0)),0)) -> 0.5 | R11: =N11*O11*P11*Q11 -> 1
A12: ST11 | C12: 351 team member | D12: Moderators + Startup Grind | E12: Referred to Acredita Portugal, later Beta-i; brought 351 an MoU with SEBRAE | F12: J | G12: Ecosystem Enablement | H12: Y | I12: C | J12: Team account | K12: Contributing | N12: =IF(OR(M12<>"",F12="X",F12="O",F12="Q"),0,1) -> 1 | O12: =IFERROR(INDEX(Weights!$B$5:$B$17,MATCH(F12,Weights!$A$5:$A$17,0)),0) -> 2 | P12: =IFERROR(INDEX(Weights!$B$21:$B$23,MATCH(I12,Weights!$A$21:$A$23,0)),0) -> 0.4 | Q12: =IF(L12<>"",IFERROR(INDEX(Weights!$B$33:$B$36,MATCH(L12,Weights!$A$33:$A$36,0)),0),IFERROR(INDEX(Weights!$B$27:$B$29,MATCH(K12,Weights!$A$27:$A$29,0)),0)) -> 0.25 | R12: =N12*O12*P12*Q12 -> 0.2
A13: ST12 | C13: 351 moderator | D13: Moderators | E13: Referred to Acredita Portugal team | F13: J | G13: Ecosystem Enablement | H13: N | I13: C | J13: Team account | K13: Contributing | N13: =IF(OR(M13<>"",F13="X",F13="O",F13="Q"),0,1) -> 1 | O13: =IFERROR(INDEX(Weights!$B$5:$B$17,MATCH(F13,Weights!$A$5:$A$17,0)),0) -> 2 | P13: =IFERROR(INDEX(Weights!$B$21:$B$23,MATCH(I13,Weights!$A$21:$A$23,0)),0) -> 0.4 | Q13: =IF(L13<>"",IFERROR(INDEX(Weights!$B$33:$B$36,MATCH(L13,Weights!$A$33:$A$36,0)),0),IFERROR(INDEX(Weights!$B$27:$B$29,MATCH(K13,Weights!$A$27:$A$29,0)),0)) -> 0.25 | R13: =N13*O13*P13*Q13 -> 0.2 | S13: Confirm role + date
A14: ST13 | C14: 351 team member | D14: Coworking Thursdays | E14: CT volunteer → moderator → represents 351 at national and international events | F14: L | G14: Ecosystem Enablement | H14: Y | I14: C | J14: Team account | K14: Direct | N14: =IF(OR(M14<>"",F14="X",F14="O",F14="Q"),0,1) -> 1 | O14: =IFERROR(INDEX(Weights!$B$5:$B$17,MATCH(F14,Weights!$A$5:$A$17,0)),0) -> 2 | P14: =IFERROR(INDEX(Weights!$B$21:$B$23,MATCH(I14,Weights!$A$21:$A$23,0)),0) -> 0.4 | Q14: =IF(L14<>"",IFERROR(INDEX(Weights!$B$33:$B$36,MATCH(L14,Weights!$A$33:$A$36,0)),0),IFERROR(INDEX(Weights!$B$27:$B$29,MATCH(K14,Weights!$A$27:$A$29,0)),0)) -> 0.5 | R14: =N14*O14*P14*Q14 -> 0.4
A15: ST14 | C15: 351 team member | D15: PTW + CT + Moderators | E15: Put forward for roles; Portuguese Women in Tech award 2024 (Community Lead) | F15: X | G15: Ecosystem Enablement | H15: Y | I15: A | J15: 351 Impact Review 2024 | K15: Contributing | N15: =IF(OR(M15<>"",F15="X",F15="O",F15="Q"),0,1) -> 0 | O15: =IFERROR(INDEX(Weights!$B$5:$B$17,MATCH(F15,Weights!$A$5:$A$17,0)),0) -> 0 | P15: =IFERROR(INDEX(Weights!$B$21:$B$23,MATCH(I15,Weights!$A$21:$A$23,0)),0) -> 1 | Q15: =IF(L15<>"",IFERROR(INDEX(Weights!$B$33:$B$36,MATCH(L15,Weights!$A$33:$A$36,0)),0),IFERROR(INDEX(Weights!$B$27:$B$29,MATCH(K15,Weights!$A$27:$A$29,0)),0)) -> 0.25 | R15: =N15*O15*P15*Q15 -> 0 | S15: Report as credibility
A16: ST15 | C16: Two 351 team members | D16: Moderators + CT | E16: Met in the 351 team and co-founded a startup; one joined the ESN board | F16: N | G16: Company Creation | H16: Y | I16: C | J16: Team account | K16: Direct | N16: =IF(OR(M16<>"",F16="X",F16="O",F16="Q"),0,1) -> 1 | O16: =IFERROR(INDEX(Weights!$B$5:$B$17,MATCH(F16,Weights!$A$5:$A$17,0)),0) -> 1.5 | P16: =IFERROR(INDEX(Weights!$B$21:$B$23,MATCH(I16,Weights!$A$21:$A$23,0)),0) -> 0.4 | Q16: =IF(L16<>"",IFERROR(INDEX(Weights!$B$33:$B$36,MATCH(L16,Weights!$A$33:$A$36,0)),0),IFERROR(INDEX(Weights!$B$27:$B$29,MATCH(K16,Weights!$A$27:$A$29,0)),0)) -> 0.5 | R16: =N16*O16*P16*Q16 -> 0.3 | S16: Get founding date
A17: ST16 | C17: 351 team member | D17: Moderators | E17: Portuguese Women in Tech award 2023; co-founder of the startup in ST15 | F17: N | G17: Company Creation | H17: Y | I17: C | J17: Team account | K17: Direct | M17: ST15 | N17: =IF(OR(M17<>"",F17="X",F17="O",F17="Q"),0,1) -> 0 | O17: =IFERROR(INDEX(Weights!$B$5:$B$17,MATCH(F17,Weights!$A$5:$A$17,0)),0) -> 1.5 | P17: =IFERROR(INDEX(Weights!$B$21:$B$23,MATCH(I17,Weights!$A$21:$A$23,0)),0) -> 0.4 | Q17: =IF(L17<>"",IFERROR(INDEX(Weights!$B$33:$B$36,MATCH(L17,Weights!$A$33:$A$36,0)),0),IFERROR(INDEX(Weights!$B$27:$B$29,MATCH(K17,Weights!$A$27:$A$29,0)),0)) -> 0.5 | R17: =N17*O17*P17*Q17 -> 0 | S17: Same outcome as ST15
A18: ST17 | C18: Weekend volunteer | D18: Startup Weekends (volunteer) | E18: Met an UltraVC partner while volunteering; offered a full-time job | F18: J | G18: Community Building | H18: N | I18: C | J18: Team account | K18: Direct | N18: =IF(OR(M18<>"",F18="X",F18="O",F18="Q"),0,1) -> 1 | O18: =IFERROR(INDEX(Weights!$B$5:$B$17,MATCH(F18,Weights!$A$5:$A$17,0)),0) -> 2 | P18: =IFERROR(INDEX(Weights!$B$21:$B$23,MATCH(I18,Weights!$A$21:$A$23,0)),0) -> 0.4 | Q18: =IF(L18<>"",IFERROR(INDEX(Weights!$B$33:$B$36,MATCH(L18,Weights!$A$33:$A$36,0)),0),IFERROR(INDEX(Weights!$B$27:$B$29,MATCH(K18,Weights!$A$27:$A$29,0)),0)) -> 0.5 | R18: =N18*O18*P18*Q18 -> 0.4 | S18: Confirm role + date
A19: ST18 | C19: 351 team member | D19: Moderators | E19: Represented 351 at YEPA / OECD; speaking and government ties | F19: X | G19: Ecosystem Enablement | H19: Y | I19: C | J19: Team account | K19: Direct | N19: =IF(OR(M19<>"",F19="X",F19="O",F19="Q"),0,1) -> 0 | O19: =IFERROR(INDEX(Weights!$B$5:$B$17,MATCH(F19,Weights!$A$5:$A$17,0)),0) -> 0 | P19: =IFERROR(INDEX(Weights!$B$21:$B$23,MATCH(I19,Weights!$A$21:$A$23,0)),0) -> 0.4 | Q19: =IF(L19<>"",IFERROR(INDEX(Weights!$B$33:$B$36,MATCH(L19,Weights!$A$33:$A$36,0)),0),IFERROR(INDEX(Weights!$B$27:$B$29,MATCH(K19,Weights!$A$27:$A$29,0)),0)) -> 0.5 | R19: =N19*O19*P19*Q19 -> 0 | S19: Report as credibility
A20: ST19 | C20: Startup Grind volunteer | D20: Startup Grind Lisbon | E20: Volunteered ~4 months, then hired by Acredita Portugal | F20: J | G20: Community Building | H20: N | I20: C | J20: Team account | K20: Direct | N20: =IF(OR(M20<>"",F20="X",F20="O",F20="Q"),0,1) -> 1 | O20: =IFERROR(INDEX(Weights!$B$5:$B$17,MATCH(F20,Weights!$A$5:$A$17,0)),0) -> 2 | P20: =IFERROR(INDEX(Weights!$B$21:$B$23,MATCH(I20,Weights!$A$21:$A$23,0)),0) -> 0.4 | Q20: =IF(L20<>"",IFERROR(INDEX(Weights!$B$33:$B$36,MATCH(L20,Weights!$A$33:$A$36,0)),0),IFERROR(INDEX(Weights!$B$27:$B$29,MATCH(K20,Weights!$A$27:$A$29,0)),0)) -> 0.5 | R20: =N20*O20*P20*Q20 -> 0.4 | S20: Confirm role + date
A21: ST20 | C21: Startup Grind volunteer | D21: Startup Grind Lisbon | E21: Volunteered, then hired by Unicorn Factory Lisboa | F21: J | G21: Community Building | H21: N | I21: C | J21: Team account | K21: Direct | N21: =IF(OR(M21<>"",F21="X",F21="O",F21="Q"),0,1) -> 1 | O21: =IFERROR(INDEX(Weights!$B$5:$B$17,MATCH(F21,Weights!$A$5:$A$17,0)),0) -> 2 | P21: =IFERROR(INDEX(Weights!$B$21:$B$23,MATCH(I21,Weights!$A$21:$A$23,0)),0) -> 0.4 | Q21: =IF(L21<>"",IFERROR(INDEX(Weights!$B$33:$B$36,MATCH(L21,Weights!$A$33:$A$36,0)),0),IFERROR(INDEX(Weights!$B$27:$B$29,MATCH(K21,Weights!$A$27:$A$29,0)),0)) -> 0.5 | R21: =N21*O21*P21*Q21 -> 0.4 | S21: Confirm role + date
A22: ST21 | C22: CLA participant | D22: Community Leaders Academy | E22: Met leaders at CLA; now co-runs initiatives in other regions (e.g. SW Loulé Women) | F22: L | G22: Ecosystem Enablement | H22: N | I22: B | J22: LinkedIn posts (participant) | K22: Direct | N22: =IF(OR(M22<>"",F22="X",F22="O",F22="Q"),0,1) -> 1 | O22: =IFERROR(INDEX(Weights!$B$5:$B$17,MATCH(F22,Weights!$A$5:$A$17,0)),0) -> 2 | P22: =IFERROR(INDEX(Weights!$B$21:$B$23,MATCH(I22,Weights!$A$21:$A$23,0)),0) -> 0.7 | Q22: =IF(L22<>"",IFERROR(INDEX(Weights!$B$33:$B$36,MATCH(L22,Weights!$A$33:$A$36,0)),0),IFERROR(INDEX(Weights!$B$27:$B$29,MATCH(K22,Weights!$A$27:$A$29,0)),0)) -> 0.5 | R22: =N22*O22*P22*Q22 -> 0.7 | S22: Count initiatives started
A23: ST22 | C23: CLA participant | D23: CT & CLA | E23: Met leaders at CLA; runs initiatives with them in other regions | F23: L | G23: Ecosystem Enablement | H23: N | I23: C | J23: Team account | K23: Direct | N23: =IF(OR(M23<>"",F23="X",F23="O",F23="Q"),0,1) -> 1 | O23: =IFERROR(INDEX(Weights!$B$5:$B$17,MATCH(F23,Weights!$A$5:$A$17,0)),0) -> 2 | P23: =IFERROR(INDEX(Weights!$B$21:$B$23,MATCH(I23,Weights!$A$21:$A$23,0)),0) -> 0.4 | Q23: =IF(L23<>"",IFERROR(INDEX(Weights!$B$33:$B$36,MATCH(L23,Weights!$A$33:$A$36,0)),0),IFERROR(INDEX(Weights!$B$27:$B$29,MATCH(K23,Weights!$A$27:$A$29,0)),0)) -> 0.5 | R23: =N23*O23*P23*Q23 -> 0.4 | S23: Name the initiatives
A24: ST23 | C24: CLA participant (corporate) | D24: CLA | E24: Became 351's champion inside Altice → led to PTW House powered by MEO | F24: N | G24: Ecosystem Enablement | H24: N | I24: C | J24: Team account | K24: Direct | N24: =IF(OR(M24<>"",F24="X",F24="O",F24="Q"),0,1) -> 1 | O24: =IFERROR(INDEX(Weights!$B$5:$B$17,MATCH(F24,Weights!$A$5:$A$17,0)),0) -> 1.5 | P24: =IFERROR(INDEX(Weights!$B$21:$B$23,MATCH(I24,Weights!$A$21:$A$23,0)),0) -> 0.4 | Q24: =IF(L24<>"",IFERROR(INDEX(Weights!$B$33:$B$36,MATCH(L24,Weights!$A$33:$A$36,0)),0),IFERROR(INDEX(Weights!$B$27:$B$29,MATCH(K24,Weights!$A$27:$A$29,0)),0)) -> 0.5 | R24: =N24*O24*P24*Q24 -> 0.3 | S24: Add MEO sponsorship value to leverage
A25: ST24 | B25: 2025 | C25: Ironhack students (team 1) | D25: Portugal Tech Week | E25: Student visual identity for PTW was implemented | F25: V | G25: Education | H25: N | I25: C | J25: Team account | K25: Direct | N25: =IF(OR(M25<>"",F25="X",F25="O",F25="Q"),0,1) -> 1 | O25: =IFERROR(INDEX(Weights!$B$5:$B$17,MATCH(F25,Weights!$A$5:$A$17,0)),0) -> 0.25 | P25: =IFERROR(INDEX(Weights!$B$21:$B$23,MATCH(I25,Weights!$A$21:$A$23,0)),0) -> 0.4 | Q25: =IF(L25<>"",IFERROR(INDEX(Weights!$B$33:$B$36,MATCH(L25,Weights!$A$33:$A$36,0)),0),IFERROR(INDEX(Weights!$B$27:$B$29,MATCH(K25,Weights!$A$27:$A$29,0)),0)) -> 0.5 | R25: =N25*O25*P25*Q25 -> 0.05
A26: ST25 | B26: 2025 | C26: Ironhack students (team 2) | D26: Portugal Tech Week | E26: PTW identity project elected best project at Ironhack | F26: V | G26: Education | H26: N | I26: C | J26: Team account | K26: Direct | M26: ST24 | N26: =IF(OR(M26<>"",F26="X",F26="O",F26="Q"),0,1) -> 0 | O26: =IFERROR(INDEX(Weights!$B$5:$B$17,MATCH(F26,Weights!$A$5:$A$17,0)),0) -> 0.25 | P26: =IFERROR(INDEX(Weights!$B$21:$B$23,MATCH(I26,Weights!$A$21:$A$23,0)),0) -> 0.4 | Q26: =IF(L26<>"",IFERROR(INDEX(Weights!$B$33:$B$36,MATCH(L26,Weights!$A$33:$A$36,0)),0),IFERROR(INDEX(Weights!$B$27:$B$29,MATCH(K26,Weights!$A$27:$A$29,0)),0)) -> 0.5 | R26: =N26*O26*P26*Q26 -> 0 | S26: Same project as ST24
A27: ST26 | B27: 2025 | C27: PTW volunteer | D27: Portugal Tech Week | E27: PTW volunteer, then recommended into a scaleup job | F27: J | G27: Community Building | H27: N | I27: C | J27: Team account | K27: Direct | N27: =IF(OR(M27<>"",F27="X",F27="O",F27="Q"),0,1) -> 1 | O27: =IFERROR(INDEX(Weights!$B$5:$B$17,MATCH(F27,Weights!$A$5:$A$17,0)),0) -> 2 | P27: =IFERROR(INDEX(Weights!$B$21:$B$23,MATCH(I27,Weights!$A$21:$A$23,0)),0) -> 0.4 | Q27: =IF(L27<>"",IFERROR(INDEX(Weights!$B$33:$B$36,MATCH(L27,Weights!$A$33:$A$36,0)),0),IFERROR(INDEX(Weights!$B$27:$B$29,MATCH(K27,Weights!$A$27:$A$29,0)),0)) -> 0.5 | R27: =N27*O27*P27*Q27 -> 0.4 | S27: Confirm company + date
A28: ST27 | B28: 2025 | C28: CreativeMornings volunteer | D28: CreativeMornings Lisbon | E28: Videographer volunteer 2 years; referred to two jobs (Startup Genome, SIM) | F28: J | G28: Community Building | H28: N | I28: C | J28: Team account | K28: Direct | N28: =IF(OR(M28<>"",F28="X",F28="O",F28="Q"),0,1) -> 1 | O28: =IFERROR(INDEX(Weights!$B$5:$B$17,MATCH(F28,Weights!$A$5:$A$17,0)),0) -> 2 | P28: =IFERROR(INDEX(Weights!$B$21:$B$23,MATCH(I28,Weights!$A$21:$A$23,0)),0) -> 0.4 | Q28: =IF(L28<>"",IFERROR(INDEX(Weights!$B$33:$B$36,MATCH(L28,Weights!$A$33:$A$36,0)),0),IFERROR(INDEX(Weights!$B$27:$B$29,MATCH(K28,Weights!$A$27:$A$29,0)),0)) -> 0.5 | R28: =N28*O28*P28*Q28 -> 0.4
A29: ST28 | B29: 2025 | C29: Software house owner | D29: CreativeMornings Lisbon | E29: His software house was referred to build a platform for NEST | F29: N | G29: Community Building | H29: N | I29: C | J29: Team account | K29: Direct | N29: =IF(OR(M29<>"",F29="X",F29="O",F29="Q"),0,1) -> 1 | O29: =IFERROR(INDEX(Weights!$B$5:$B$17,MATCH(F29,Weights!$A$5:$A$17,0)),0) -> 1.5 | P29: =IFERROR(INDEX(Weights!$B$21:$B$23,MATCH(I29,Weights!$A$21:$A$23,0)),0) -> 0.4 | Q29: =IF(L29<>"",IFERROR(INDEX(Weights!$B$33:$B$36,MATCH(L29,Weights!$A$33:$A$36,0)),0),IFERROR(INDEX(Weights!$B$27:$B$29,MATCH(K29,Weights!$A$27:$A$29,0)),0)) -> 0.5 | R29: =N29*O29*P29*Q29 -> 0.3 | S29: Get contract value
A30: ST29 | B30: 2025 | C30: All teams, SW Évora | D30: Startup Weekend Évora | E30: All teams received a social incubation voucher at Fundação Eugénio de Almeida | F30: S2 | G30: Company Creation | H30: N | I30: B | J30: LinkedIn posts (two founders) | K30: Direct | N30: =IF(OR(M30<>"",F30="X",F30="O",F30="Q"),0,1) -> 1 | O30: =IFERROR(INDEX(Weights!$B$5:$B$17,MATCH(F30,Weights!$A$5:$A$17,0)),0) -> 2 | P30: =IFERROR(INDEX(Weights!$B$21:$B$23,MATCH(I30,Weights!$A$21:$A$23,0)),0) -> 0.7 | Q30: =IF(L30<>"",IFERROR(INDEX(Weights!$B$33:$B$36,MATCH(L30,Weights!$A$33:$A$36,0)),0),IFERROR(INDEX(Weights!$B$27:$B$29,MATCH(K30,Weights!$A$27:$A$29,0)),0)) -> 0.5 | R30: =N30*O30*P30*Q30 -> 0.7 | S30: Get the voucher letter
A31: ST30 | B31: 2025 | C31: PTW volunteer | D31: PTW + Membership | E31: Referred to Imatch; now organises SIMCONF and other projects | F31: J | G31: Community Building | H31: N | I31: C | J31: Team account | K31: Direct | N31: =IF(OR(M31<>"",F31="X",F31="O",F31="Q"),0,1) -> 1 | O31: =IFERROR(INDEX(Weights!$B$5:$B$17,MATCH(F31,Weights!$A$5:$A$17,0)),0) -> 2 | P31: =IFERROR(INDEX(Weights!$B$21:$B$23,MATCH(I31,Weights!$A$21:$A$23,0)),0) -> 0.4 | Q31: =IF(L31<>"",IFERROR(INDEX(Weights!$B$33:$B$36,MATCH(L31,Weights!$A$33:$A$36,0)),0),IFERROR(INDEX(Weights!$B$27:$B$29,MATCH(K31,Weights!$A$27:$A$29,0)),0)) -> 0.5 | R31: =N31*O31*P31*Q31 -> 0.4
A32: ST31 | B32: 2025 | C32: Startuppers participant | D32: Startuppers | E32: Says 2 free Startuppers sessions gave more value than a month at an incubator | F32: V | G32: Education | H32: N | I32: B | J32: His own written feedback | K32: Direct | N32: =IF(OR(M32<>"",F32="X",F32="O",F32="Q"),0,1) -> 1 | O32: =IFERROR(INDEX(Weights!$B$5:$B$17,MATCH(F32,Weights!$A$5:$A$17,0)),0) -> 0.25 | P32: =IFERROR(INDEX(Weights!$B$21:$B$23,MATCH(I32,Weights!$A$21:$A$23,0)),0) -> 0.7 | Q32: =IF(L32<>"",IFERROR(INDEX(Weights!$B$33:$B$36,MATCH(L32,Weights!$A$33:$A$36,0)),0),IFERROR(INDEX(Weights!$B$27:$B$29,MATCH(K32,Weights!$A$27:$A$29,0)),0)) -> 0.5 | R32: =N32*O32*P32*Q32 -> 0.0875
A33: ST32 | B33: 2025 | C33: SW Coimbra startup | D33: Startup Weekend Coimbra | E33: Born at SW Coimbra; accelerated by IPN; pitched at Coimbra Investors Conference | F33: S2 | G33: Company Creation | H33: N | I33: B | J33: PRR file lists it as created at SW Coimbra; acceleration told by team | K33: Direct | N33: =IF(OR(M33<>"",F33="X",F33="O",F33="Q"),0,1) -> 1 | O33: =IFERROR(INDEX(Weights!$B$5:$B$17,MATCH(F33,Weights!$A$5:$A$17,0)),0) -> 2 | P33: =IFERROR(INDEX(Weights!$B$21:$B$23,MATCH(I33,Weights!$A$21:$A$23,0)),0) -> 0.7 | Q33: =IF(L33<>"",IFERROR(INDEX(Weights!$B$33:$B$36,MATCH(L33,Weights!$A$33:$A$36,0)),0),IFERROR(INDEX(Weights!$B$27:$B$29,MATCH(K33,Weights!$A$27:$A$29,0)),0)) -> 0.5 | R33: =N33*O33*P33*Q33 -> 0.7 | S33: Get IPN confirmation
A34: ST33 | B34: 2025 | C34: Startup Clinics participants | D34: Startup Clinics | E34: Founders built their own MVP instead of outsourcing (quote) | F34: V | G34: Education | H34: N | I34: B | J34: Startup Clinics feedback sheet | K34: Direct | N34: =IF(OR(M34<>"",F34="X",F34="O",F34="Q"),0,1) -> 1 | O34: =IFERROR(INDEX(Weights!$B$5:$B$17,MATCH(F34,Weights!$A$5:$A$17,0)),0) -> 0.25 | P34: =IFERROR(INDEX(Weights!$B$21:$B$23,MATCH(I34,Weights!$A$21:$A$23,0)),0) -> 0.7 | Q34: =IF(L34<>"",IFERROR(INDEX(Weights!$B$33:$B$36,MATCH(L34,Weights!$A$33:$A$36,0)),0),IFERROR(INDEX(Weights!$B$27:$B$29,MATCH(K34,Weights!$A$27:$A$29,0)),0)) -> 0.5 | R34: =N34*O34*P34*Q34 -> 0.0875 | S34: Count how many built an MVP
A35: ST34 | B35: 2025 | C35: Community member (now abroad) | D35: Community | E35: Wants to replicate 351 in South Africa; 351 got him out of his shell and unstuck | F35: V | G35: Community Building | H35: N | I35: B | J35: Message to 351 | K35: Direct | N35: =IF(OR(M35<>"",F35="X",F35="O",F35="Q"),0,1) -> 1 | O35: =IFERROR(INDEX(Weights!$B$5:$B$17,MATCH(F35,Weights!$A$5:$A$17,0)),0) -> 0.25 | P35: =IFERROR(INDEX(Weights!$B$21:$B$23,MATCH(I35,Weights!$A$21:$A$23,0)),0) -> 0.7 | Q35: =IF(L35<>"",IFERROR(INDEX(Weights!$B$33:$B$36,MATCH(L35,Weights!$A$33:$A$36,0)),0),IFERROR(INDEX(Weights!$B$27:$B$29,MATCH(K35,Weights!$A$27:$A$29,0)),0)) -> 0.5 | R35: =N35*O35*P35*Q35 -> 0.0875
A36: ST35 | B36: 2025 | C36: 13-year-old participant (SW Albufeira) | D36: Startup Weekend Albufeira | E36: 13-year-old built a startup in 54 hours; national press | F36: S1 | G36: Ideation | H36: N | I36: A | J36: Press: thenextbigidea.pt | K36: Direct | M36: REC-S1 | N36: =IF(OR(M36<>"",F36="X",F36="O",F36="Q"),0,1) -> 0 | O36: =IFERROR(INDEX(Weights!$B$5:$B$17,MATCH(F36,Weights!$A$5:$A$17,0)),0) -> 1 | P36: =IFERROR(INDEX(Weights!$B$21:$B$23,MATCH(I36,Weights!$A$21:$A$23,0)),0) -> 1 | Q36: =IF(L36<>"",IFERROR(INDEX(Weights!$B$33:$B$36,MATCH(L36,Weights!$A$33:$A$36,0)),0),IFERROR(INDEX(Weights!$B$27:$B$29,MATCH(K36,Weights!$A$27:$A$29,0)),0)) -> 0.5 | R36: =N36*O36*P36*Q36 -> 0 | S36: Counted in records (SW Albufeira); keep as illustration
A37: ST36 | B37: 2025 | C37: Startuppers founder | D37: Startuppers | E37: Won Canopy + Startup23 demo day; says Startuppers fixed her pitch | F37: S4 | G37: Education | H37: N | I37: C | J37: Team account | K37: Contributing | N37: =IF(OR(M37<>"",F37="X",F37="O",F37="Q"),0,1) -> 1 | O37: =IFERROR(INDEX(Weights!$B$5:$B$17,MATCH(F37,Weights!$A$5:$A$17,0)),0) -> 2 | P37: =IFERROR(INDEX(Weights!$B$21:$B$23,MATCH(I37,Weights!$A$21:$A$23,0)),0) -> 0.4 | Q37: =IF(L37<>"",IFERROR(INDEX(Weights!$B$33:$B$36,MATCH(L37,Weights!$A$33:$A$36,0)),0),IFERROR(INDEX(Weights!$B$27:$B$29,MATCH(K37,Weights!$A$27:$A$29,0)),0)) -> 0.25 | R37: =N37*O37*P37*Q37 -> 0.2 | S37: Get a post or quote
A38: ST37 | B38: 2025 | C38: Startuppers volunteer | D38: Startuppers (volunteer) | E38: Volunteer recommended for a role at Nova SBE | F38: J | G38: Community Building | H38: N | I38: C | J38: Team account | K38: Direct | N38: =IF(OR(M38<>"",F38="X",F38="O",F38="Q"),0,1) -> 1 | O38: =IFERROR(INDEX(Weights!$B$5:$B$17,MATCH(F38,Weights!$A$5:$A$17,0)),0) -> 2 | P38: =IFERROR(INDEX(Weights!$B$21:$B$23,MATCH(I38,Weights!$A$21:$A$23,0)),0) -> 0.4 | Q38: =IF(L38<>"",IFERROR(INDEX(Weights!$B$33:$B$36,MATCH(L38,Weights!$A$33:$A$36,0)),0),IFERROR(INDEX(Weights!$B$27:$B$29,MATCH(K38,Weights!$A$27:$A$29,0)),0)) -> 0.5 | R38: =N38*O38*P38*Q38 -> 0.4
A39: ST38 | B39: 2025 | C39: 351 team member | D39: Moderators | E39: Unicorn Factory Awards 2025 — International Person of the Year (finalist) | F39: X | G39: Ecosystem Enablement | H39: Y | I39: C | J39: Team account | K39: Unclear | N39: =IF(OR(M39<>"",F39="X",F39="O",F39="Q"),0,1) -> 0 | O39: =IFERROR(INDEX(Weights!$B$5:$B$17,MATCH(F39,Weights!$A$5:$A$17,0)),0) -> 0 | P39: =IFERROR(INDEX(Weights!$B$21:$B$23,MATCH(I39,Weights!$A$21:$A$23,0)),0) -> 0.4 | Q39: =IF(L39<>"",IFERROR(INDEX(Weights!$B$33:$B$36,MATCH(L39,Weights!$A$33:$A$36,0)),0),IFERROR(INDEX(Weights!$B$27:$B$29,MATCH(K39,Weights!$A$27:$A$29,0)),0)) -> 0.1 | R39: =N39*O39*P39*Q39 -> 0 | S39: Report as credibility
A40: ST39 | B40: 2025 | C40: 351 team member | D40: Moderators | E40: Unicorn Factory Awards 2025 — International Person of the Year (finalist) | F40: X | G40: Ecosystem Enablement | H40: Y | I40: C | J40: Team account | K40: Unclear | N40: =IF(OR(M40<>"",F40="X",F40="O",F40="Q"),0,1) -> 0 | O40: =IFERROR(INDEX(Weights!$B$5:$B$17,MATCH(F40,Weights!$A$5:$A$17,0)),0) -> 0 | P40: =IFERROR(INDEX(Weights!$B$21:$B$23,MATCH(I40,Weights!$A$21:$A$23,0)),0) -> 0.4 | Q40: =IF(L40<>"",IFERROR(INDEX(Weights!$B$33:$B$36,MATCH(L40,Weights!$A$33:$A$36,0)),0),IFERROR(INDEX(Weights!$B$27:$B$29,MATCH(K40,Weights!$A$27:$A$29,0)),0)) -> 0.1 | R40: =N40*O40*P40*Q40 -> 0 | S40: Report as credibility
A41: ST40 | B41: 2025 | C41: 351 team member | D41: Moderators | E41: Unicorn Factory Awards 2025 — International Person of the Year (finalist) | F41: X | G41: Ecosystem Enablement | H41: Y | I41: A | J41: 351startups.com (checked 15 Oct 2026) | K41: Unclear | N41: =IF(OR(M41<>"",F41="X",F41="O",F41="Q"),0,1) -> 0 | O41: =IFERROR(INDEX(Weights!$B$5:$B$17,MATCH(F41,Weights!$A$5:$A$17,0)),0) -> 0 | P41: =IFERROR(INDEX(Weights!$B$21:$B$23,MATCH(I41,Weights!$A$21:$A$23,0)),0) -> 1 | Q41: =IF(L41<>"",IFERROR(INDEX(Weights!$B$33:$B$36,MATCH(L41,Weights!$A$33:$A$36,0)),0),IFERROR(INDEX(Weights!$B$27:$B$29,MATCH(K41,Weights!$A$27:$A$29,0)),0)) -> 0.1 | R41: =N41*O41*P41*Q41 -> 0 | S41: Report as credibility
A42: ST41 | B42: 2025 | C42: Weekend participant | D42: Startup Weekend | E42: Portuguese Women in Tech 2025 — Community award | F42: R | G42: Ecosystem Enablement | H42: N | I42: C | J42: Team account | K42: Contributing | N42: =IF(OR(M42<>"",F42="X",F42="O",F42="Q"),0,1) -> 1 | O42: =IFERROR(INDEX(Weights!$B$5:$B$17,MATCH(F42,Weights!$A$5:$A$17,0)),0) -> 0.5 | P42: =IFERROR(INDEX(Weights!$B$21:$B$23,MATCH(I42,Weights!$A$21:$A$23,0)),0) -> 0.4 | Q42: =IF(L42<>"",IFERROR(INDEX(Weights!$B$33:$B$36,MATCH(L42,Weights!$A$33:$A$36,0)),0),IFERROR(INDEX(Weights!$B$27:$B$29,MATCH(K42,Weights!$A$27:$A$29,0)),0)) -> 0.25 | R42: =N42*O42*P42*Q42 -> 0.05 | S42: Get award link
A43: ST42 | B43: 2025 | C43: PTW volunteer | D43: Portugal Tech Week | E43: PTW volunteer → hired by Tech Plane → referred on | F43: J | G43: Community Building | H43: N | I43: C | J43: Team account | K43: Direct | N43: =IF(OR(M43<>"",F43="X",F43="O",F43="Q"),0,1) -> 1 | O43: =IFERROR(INDEX(Weights!$B$5:$B$17,MATCH(F43,Weights!$A$5:$A$17,0)),0) -> 2 | P43: =IFERROR(INDEX(Weights!$B$21:$B$23,MATCH(I43,Weights!$A$21:$A$23,0)),0) -> 0.4 | Q43: =IF(L43<>"",IFERROR(INDEX(Weights!$B$33:$B$36,MATCH(L43,Weights!$A$33:$A$36,0)),0),IFERROR(INDEX(Weights!$B$27:$B$29,MATCH(K43,Weights!$A$27:$A$29,0)),0)) -> 0.5 | R43: =N43*O43*P43*Q43 -> 0.4
A44: ST43 | B44: 2025 | C44: 10 volunteers | D44: Web Summit tickets | E44: Volunteers got Web Summit tickets | F44: O | G44: Community Building | H44: N | I44: A | J44: 351 ticket records | K44: Direct | N44: =IF(OR(M44<>"",F44="X",F44="O",F44="Q"),0,1) -> 0 | O44: =IFERROR(INDEX(Weights!$B$5:$B$17,MATCH(F44,Weights!$A$5:$A$17,0)),0) -> 0 | P44: =IFERROR(INDEX(Weights!$B$21:$B$23,MATCH(I44,Weights!$A$21:$A$23,0)),0) -> 1 | Q44: =IF(L44<>"",IFERROR(INDEX(Weights!$B$33:$B$36,MATCH(L44,Weights!$A$33:$A$36,0)),0),IFERROR(INDEX(Weights!$B$27:$B$29,MATCH(K44,Weights!$A$27:$A$29,0)),0)) -> 0.5 | R44: =N44*O44*P44*Q44 -> 0 | S44: Benefit, not outcome
A45: ST44 | B45: 2025 | C45: Two FI founders | D45: Founder Institute | E45: Free Web Summit tickets via FI | F45: O | G45: Company Creation | H45: N | I45: C | J45: Team account | K45: Direct | N45: =IF(OR(M45<>"",F45="X",F45="O",F45="Q"),0,1) -> 0 | O45: =IFERROR(INDEX(Weights!$B$5:$B$17,MATCH(F45,Weights!$A$5:$A$17,0)),0) -> 0 | P45: =IFERROR(INDEX(Weights!$B$21:$B$23,MATCH(I45,Weights!$A$21:$A$23,0)),0) -> 0.4 | Q45: =IF(L45<>"",IFERROR(INDEX(Weights!$B$33:$B$36,MATCH(L45,Weights!$A$33:$A$36,0)),0),IFERROR(INDEX(Weights!$B$27:$B$29,MATCH(K45,Weights!$A$27:$A$29,0)),0)) -> 0.5 | R45: =N45*O45*P45*Q45 -> 0 | S45: Benefit, not outcome
A46: ST45 | B46: 2025 | C46: Weekend founder (SW Albufeira) | D46: SW Albufeira → Startuppers → FI | E46: Selected for Unicorn Factory Lisboa incubation; Santander X pre-selection | F46: S2 | G46: Company Creation | H46: N | I46: A | J46: PRR evidence file (documented pathway) | K46: Direct | N46: =IF(OR(M46<>"",F46="X",F46="O",F46="Q"),0,1) -> 1 | O46: =IFERROR(INDEX(Weights!$B$5:$B$17,MATCH(F46,Weights!$A$5:$A$17,0)),0) -> 2 | P46: =IFERROR(INDEX(Weights!$B$21:$B$23,MATCH(I46,Weights!$A$21:$A$23,0)),0) -> 1 | Q46: =IF(L46<>"",IFERROR(INDEX(Weights!$B$33:$B$36,MATCH(L46,Weights!$A$33:$A$36,0)),0),IFERROR(INDEX(Weights!$B$27:$B$29,MATCH(K46,Weights!$A$27:$A$29,0)),0)) -> 0.5 | R46: =N46*O46*P46*Q46 -> 1
A47: ST46 | B47: 2025 | C47: FI founder | D47: Founder Institute | E47: Accepted into Intertrade / Enterprise Ireland female founder programme; first consulting client | F47: S2 | G47: Company Creation | H47: N | I47: B | J47: Her own message | K47: Contributing | N47: =IF(OR(M47<>"",F47="X",F47="O",F47="Q"),0,1) -> 1 | O47: =IFERROR(INDEX(Weights!$B$5:$B$17,MATCH(F47,Weights!$A$5:$A$17,0)),0) -> 2 | P47: =IFERROR(INDEX(Weights!$B$21:$B$23,MATCH(I47,Weights!$A$21:$A$23,0)),0) -> 0.7 | Q47: =IF(L47<>"",IFERROR(INDEX(Weights!$B$33:$B$36,MATCH(L47,Weights!$A$33:$A$36,0)),0),IFERROR(INDEX(Weights!$B$27:$B$29,MATCH(K47,Weights!$A$27:$A$29,0)),0)) -> 0.25 | R47: =N47*O47*P47*Q47 -> 0.35
A48: ST47 | B48: 2025 | C48: Founder (PTW Palace) | D48: PTW Palace | E48: Co-founders travelled to Lisbon because of the PTW Palace | F48: V | G48: Community Building | H48: N | I48: B | J48: Own message + Drive file | K48: Direct | N48: =IF(OR(M48<>"",F48="X",F48="O",F48="Q"),0,1) -> 1 | O48: =IFERROR(INDEX(Weights!$B$5:$B$17,MATCH(F48,Weights!$A$5:$A$17,0)),0) -> 0.25 | P48: =IFERROR(INDEX(Weights!$B$21:$B$23,MATCH(I48,Weights!$A$21:$A$23,0)),0) -> 0.7 | Q48: =IF(L48<>"",IFERROR(INDEX(Weights!$B$33:$B$36,MATCH(L48,Weights!$A$33:$A$36,0)),0),IFERROR(INDEX(Weights!$B$27:$B$29,MATCH(K48,Weights!$A$27:$A$29,0)),0)) -> 0.5 | R48: =N48*O48*P48*Q48 -> 0.0875
A49: ST48 | B49: 2026 | C49: Community member | D49: EU-Startups Top 100 Women in Tech | E49: Listed in EU-Startups Top 100 Women in Tech (sheet text needs fixing) | F49: R | G49: Ecosystem Enablement | H49: N | I49: C | J49: Sheet row has wrong text | K49: Unclear | N49: =IF(OR(M49<>"",F49="X",F49="O",F49="Q"),0,1) -> 1 | O49: =IFERROR(INDEX(Weights!$B$5:$B$17,MATCH(F49,Weights!$A$5:$A$17,0)),0) -> 0.5 | P49: =IFERROR(INDEX(Weights!$B$21:$B$23,MATCH(I49,Weights!$A$21:$A$23,0)),0) -> 0.4 | Q49: =IF(L49<>"",IFERROR(INDEX(Weights!$B$33:$B$36,MATCH(L49,Weights!$A$33:$A$36,0)),0),IFERROR(INDEX(Weights!$B$27:$B$29,MATCH(K49,Weights!$A$27:$A$29,0)),0)) -> 0.1 | R49: =N49*O49*P49*Q49 -> 0.02 | S49: FIX sheet row text
A50: ST49 | B50: 2026 | C50: Closure team (SW Loulé Women) | D50: Techstars Startup Weekend Loulé | E50: Winning team selected for Techstars global competition: top 10 of 38 cities | F50: S4 | G50: Ideation | H50: N | I50: A | J50: Press: Executive Digest | K50: Direct | N50: =IF(OR(M50<>"",F50="X",F50="O",F50="Q"),0,1) -> 1 | O50: =IFERROR(INDEX(Weights!$B$5:$B$17,MATCH(F50,Weights!$A$5:$A$17,0)),0) -> 2 | P50: =IFERROR(INDEX(Weights!$B$21:$B$23,MATCH(I50,Weights!$A$21:$A$23,0)),0) -> 1 | Q50: =IF(L50<>"",IFERROR(INDEX(Weights!$B$33:$B$36,MATCH(L50,Weights!$A$33:$A$36,0)),0),IFERROR(INDEX(Weights!$B$27:$B$29,MATCH(K50,Weights!$A$27:$A$29,0)),0)) -> 0.5 | R50: =N50*O50*P50*Q50 -> 1
A51: ST50 | B51: 2026 | C51: Weekend founder (SW Albufeira) | D51: SW Albufeira → Startuppers → FI | E51: Weekend → Startuppers twice → Founder Institute demo day | F51: S2 | G51: Company Creation | H51: N | I51: A | J51: PRR evidence file (documented pathway) | K51: Direct | N51: =IF(OR(M51<>"",F51="X",F51="O",F51="Q"),0,1) -> 1 | O51: =IFERROR(INDEX(Weights!$B$5:$B$17,MATCH(F51,Weights!$A$5:$A$17,0)),0) -> 2 | P51: =IFERROR(INDEX(Weights!$B$21:$B$23,MATCH(I51,Weights!$A$21:$A$23,0)),0) -> 1 | Q51: =IF(L51<>"",IFERROR(INDEX(Weights!$B$33:$B$36,MATCH(L51,Weights!$A$33:$A$36,0)),0),IFERROR(INDEX(Weights!$B$27:$B$29,MATCH(K51,Weights!$A$27:$A$29,0)),0)) -> 0.5 | R51: =N51*O51*P51*Q51 -> 1
A52: ST51 | B52: 2026 | C52: Workshop attendee | D52: FI workshop: $1B Solo Founder | E52: Launched his product the day after the talk | F52: S3 | G52: Education | H52: N | I52: B | J52: His LinkedIn post | K52: Direct | N52: =IF(OR(M52<>"",F52="X",F52="O",F52="Q"),0,1) -> 1 | O52: =IFERROR(INDEX(Weights!$B$5:$B$17,MATCH(F52,Weights!$A$5:$A$17,0)),0) -> 3 | P52: =IFERROR(INDEX(Weights!$B$21:$B$23,MATCH(I52,Weights!$A$21:$A$23,0)),0) -> 0.7 | Q52: =IF(L52<>"",IFERROR(INDEX(Weights!$B$33:$B$36,MATCH(L52,Weights!$A$33:$A$36,0)),0),IFERROR(INDEX(Weights!$B$27:$B$29,MATCH(K52,Weights!$A$27:$A$29,0)),0)) -> 0.5 | R52: =N52*O52*P52*Q52 -> 1.05 | S52: Ask about traction
A53: ST52 | B53: 2026 | C53: Founder (FI speaker) | D53: Networking event | E53: Founder says her first-ever entrepreneurship event was a 351 event | F53: V | G53: Community Building | H53: N | I53: C | J53: Said on stage (team account) | K53: Contributing | N53: =IF(OR(M53<>"",F53="X",F53="O",F53="Q"),0,1) -> 1 | O53: =IFERROR(INDEX(Weights!$B$5:$B$17,MATCH(F53,Weights!$A$5:$A$17,0)),0) -> 0.25 | P53: =IFERROR(INDEX(Weights!$B$21:$B$23,MATCH(I53,Weights!$A$21:$A$23,0)),0) -> 0.4 | Q53: =IF(L53<>"",IFERROR(INDEX(Weights!$B$33:$B$36,MATCH(L53,Weights!$A$33:$A$36,0)),0),IFERROR(INDEX(Weights!$B$27:$B$29,MATCH(K53,Weights!$A$27:$A$29,0)),0)) -> 0.25 | R53: =N53*O53*P53*Q53 -> 0.025 | S53: Get a written quote
A54: ST53 | B54: 2026 | C54: Workshop attendee | D54: FI workshop: $1B Solo Founder | E54: Built an automated prospecting tool after the talk | F54: S3 | G54: Education | H54: N | I54: B | J54: His email | K54: Direct | N54: =IF(OR(M54<>"",F54="X",F54="O",F54="Q"),0,1) -> 1 | O54: =IFERROR(INDEX(Weights!$B$5:$B$17,MATCH(F54,Weights!$A$5:$A$17,0)),0) -> 3 | P54: =IFERROR(INDEX(Weights!$B$21:$B$23,MATCH(I54,Weights!$A$21:$A$23,0)),0) -> 0.7 | Q54: =IF(L54<>"",IFERROR(INDEX(Weights!$B$33:$B$36,MATCH(L54,Weights!$A$33:$A$36,0)),0),IFERROR(INDEX(Weights!$B$27:$B$29,MATCH(K54,Weights!$A$27:$A$29,0)),0)) -> 0.5 | R54: =N54*O54*P54*Q54 -> 1.05 | S54: Ask about results
A55: ST54 | B55: 2026 | C55: Workshop attendee | D55: FI workshop: AI & Growth | E55: "One of the best talks I've attended" | F55: V | G55: Education | H55: N | I55: B | J55: Her message | K55: Direct | N55: =IF(OR(M55<>"",F55="X",F55="O",F55="Q"),0,1) -> 1 | O55: =IFERROR(INDEX(Weights!$B$5:$B$17,MATCH(F55,Weights!$A$5:$A$17,0)),0) -> 0.25 | P55: =IFERROR(INDEX(Weights!$B$21:$B$23,MATCH(I55,Weights!$A$21:$A$23,0)),0) -> 0.7 | Q55: =IF(L55<>"",IFERROR(INDEX(Weights!$B$33:$B$36,MATCH(L55,Weights!$A$33:$A$36,0)),0),IFERROR(INDEX(Weights!$B$27:$B$29,MATCH(K55,Weights!$A$27:$A$29,0)),0)) -> 0.5 | R55: =N55*O55*P55*Q55 -> 0.0875
A56: ST55 | B56: 2026 | C56: Workshop attendee | D56: FI workshop: AI & Growth | E56: "One of the best workshops I've ever attended"; asked for the CAC tool | F56: V | G56: Education | H56: N | I56: B | J56: Her message | K56: Direct | N56: =IF(OR(M56<>"",F56="X",F56="O",F56="Q"),0,1) -> 1 | O56: =IFERROR(INDEX(Weights!$B$5:$B$17,MATCH(F56,Weights!$A$5:$A$17,0)),0) -> 0.25 | P56: =IFERROR(INDEX(Weights!$B$21:$B$23,MATCH(I56,Weights!$A$21:$A$23,0)),0) -> 0.7 | Q56: =IF(L56<>"",IFERROR(INDEX(Weights!$B$33:$B$36,MATCH(L56,Weights!$A$33:$A$36,0)),0),IFERROR(INDEX(Weights!$B$27:$B$29,MATCH(K56,Weights!$A$27:$A$29,0)),0)) -> 0.5 | R56: =N56*O56*P56*Q56 -> 0.0875
A57: ST56 | B57: 2026 | C57: Two FI founders | D57: Founder Institute | E57: Met at FI and piloted each other's products | F57: N | G57: Company Creation | H57: N | I57: C | J57: Team account; one founder in PRR file (FI demo day) | K57: Direct | N57: =IF(OR(M57<>"",F57="X",F57="O",F57="Q"),0,1) -> 1 | O57: =IFERROR(INDEX(Weights!$B$5:$B$17,MATCH(F57,Weights!$A$5:$A$17,0)),0) -> 1.5 | P57: =IFERROR(INDEX(Weights!$B$21:$B$23,MATCH(I57,Weights!$A$21:$A$23,0)),0) -> 0.4 | Q57: =IF(L57<>"",IFERROR(INDEX(Weights!$B$33:$B$36,MATCH(L57,Weights!$A$33:$A$36,0)),0),IFERROR(INDEX(Weights!$B$27:$B$29,MATCH(K57,Weights!$A$27:$A$29,0)),0)) -> 0.5 | R57: =N57*O57*P57*Q57 -> 0.3 | S57: Get a quote
A58: ST57 | B58: 2026 | C58: FI founder (AI startup) | D58: Founder Institute | E58: Paid enterprise pilot; $30M leads processed; client revenue 2x; revenue-positive; hired 2; talks with Founder Capital and a16z | F58: S3 | G58: Scale | H58: N | I58: B | J58: His own message | K58: Contributing | N58: =IF(OR(M58<>"",F58="X",F58="O",F58="Q"),0,1) -> 1 | O58: =IFERROR(INDEX(Weights!$B$5:$B$17,MATCH(F58,Weights!$A$5:$A$17,0)),0) -> 3 | P58: =IFERROR(INDEX(Weights!$B$21:$B$23,MATCH(I58,Weights!$A$21:$A$23,0)),0) -> 0.7 | Q58: =IF(L58<>"",IFERROR(INDEX(Weights!$B$33:$B$36,MATCH(L58,Weights!$A$33:$A$36,0)),0),IFERROR(INDEX(Weights!$B$27:$B$29,MATCH(K58,Weights!$A$27:$A$29,0)),0)) -> 0.25 | R58: =N58*O58*P58*Q58 -> 0.525 | S58: Ask what FI/351 changed
A59: ST58 | B59: 2026 | C59: SeedSight (startup) | D59: EU Apply AI award referral | E59: 351 referred them to the European Commission; shortlisted top 10 | F59: S4 | G59: Scale | H59: N | I59: A | J59: European Commission page | K59: Direct | N59: =IF(OR(M59<>"",F59="X",F59="O",F59="Q"),0,1) -> 1 | O59: =IFERROR(INDEX(Weights!$B$5:$B$17,MATCH(F59,Weights!$A$5:$A$17,0)),0) -> 2 | P59: =IFERROR(INDEX(Weights!$B$21:$B$23,MATCH(I59,Weights!$A$21:$A$23,0)),0) -> 1 | Q59: =IF(L59<>"",IFERROR(INDEX(Weights!$B$33:$B$36,MATCH(L59,Weights!$A$33:$A$36,0)),0),IFERROR(INDEX(Weights!$B$27:$B$29,MATCH(K59,Weights!$A$27:$A$29,0)),0)) -> 0.5 | R59: =N59*O59*P59*Q59 -> 1
A60: ST59 | B60: 2026 | C60: BlueOasis (startup) | D60: EU Apply AI award referral | E60: 351 referred them to the European Commission; shortlisted top 10 | F60: S4 | G60: Scale | H60: N | I60: A | J60: European Commission page | K60: Direct | N60: =IF(OR(M60<>"",F60="X",F60="O",F60="Q"),0,1) -> 1 | O60: =IFERROR(INDEX(Weights!$B$5:$B$17,MATCH(F60,Weights!$A$5:$A$17,0)),0) -> 2 | P60: =IFERROR(INDEX(Weights!$B$21:$B$23,MATCH(I60,Weights!$A$21:$A$23,0)),0) -> 1 | Q60: =IF(L60<>"",IFERROR(INDEX(Weights!$B$33:$B$36,MATCH(L60,Weights!$A$33:$A$36,0)),0),IFERROR(INDEX(Weights!$B$27:$B$29,MATCH(K60,Weights!$A$27:$A$29,0)),0)) -> 0.5 | R60: =N60*O60*P60*Q60 -> 1
A61: ST60 | B61: 2026 | C61: Founder (PTW volunteer) | D61: PTW volunteer → Startup Weekend | E61: Says 351 perks, tools and intros were important; wants 351 logo on site | F61: V | G61: Company Creation | H61: N | I61: A | J61: Their message + PRR mediated-services record (11 tools) | K61: Direct | N61: =IF(OR(M61<>"",F61="X",F61="O",F61="Q"),0,1) -> 1 | O61: =IFERROR(INDEX(Weights!$B$5:$B$17,MATCH(F61,Weights!$A$5:$A$17,0)),0) -> 0.25 | P61: =IFERROR(INDEX(Weights!$B$21:$B$23,MATCH(I61,Weights!$A$21:$A$23,0)),0) -> 1 | Q61: =IF(L61<>"",IFERROR(INDEX(Weights!$B$33:$B$36,MATCH(L61,Weights!$A$33:$A$36,0)),0),IFERROR(INDEX(Weights!$B$27:$B$29,MATCH(K61,Weights!$A$27:$A$29,0)),0)) -> 0.5 | R61: =N61*O61*P61*Q61 -> 0.125
A62: ST61 | B62: 2026 | C62: Founder (PTW volunteer) | D62: PTW volunteer → Startup Weekend | E62: LinkedIn post (same person as ST60) | F62: V | G62: Company Creation | H62: N | I62: B | J62: LinkedIn | K62: Direct | M62: ST60 | N62: =IF(OR(M62<>"",F62="X",F62="O",F62="Q"),0,1) -> 0 | O62: =IFERROR(INDEX(Weights!$B$5:$B$17,MATCH(F62,Weights!$A$5:$A$17,0)),0) -> 0.25 | P62: =IFERROR(INDEX(Weights!$B$21:$B$23,MATCH(I62,Weights!$A$21:$A$23,0)),0) -> 0.7 | Q62: =IF(L62<>"",IFERROR(INDEX(Weights!$B$33:$B$36,MATCH(L62,Weights!$A$33:$A$36,0)),0),IFERROR(INDEX(Weights!$B$27:$B$29,MATCH(K62,Weights!$A$27:$A$29,0)),0)) -> 0.5 | R62: =N62*O62*P62*Q62 -> 0 | S62: Same person as ST60
A63: ST62 | B63: 2026 | C63: Volunteer | D63: Volunteer | E63: Volunteer nominated International Personality of the Year | F63: R | G63: Ecosystem Enablement | H63: N | I63: C | J63: Team account | K63: Contributing | N63: =IF(OR(M63<>"",F63="X",F63="O",F63="Q"),0,1) -> 1 | O63: =IFERROR(INDEX(Weights!$B$5:$B$17,MATCH(F63,Weights!$A$5:$A$17,0)),0) -> 0.5 | P63: =IFERROR(INDEX(Weights!$B$21:$B$23,MATCH(I63,Weights!$A$21:$A$23,0)),0) -> 0.4 | Q63: =IF(L63<>"",IFERROR(INDEX(Weights!$B$33:$B$36,MATCH(L63,Weights!$A$33:$A$36,0)),0),IFERROR(INDEX(Weights!$B$27:$B$29,MATCH(K63,Weights!$A$27:$A$29,0)),0)) -> 0.25 | R63: =N63*O63*P63*Q63 -> 0.05 | S63: Get award link
A64: ST63 | B64: 2026 | C64: Startup Grind volunteer and founder | D64: Startup Grind (volunteer) | E64: Long-time volunteer while building a startup; shortlisted and won Portfolio Day at Unicorn Factory awards 2026 | F64: S4 | G64: Scale | H64: N | I64: B | J64: His LinkedIn post | K64: Contributing | N64: =IF(OR(M64<>"",F64="X",F64="O",F64="Q"),0,1) -> 1 | O64: =IFERROR(INDEX(Weights!$B$5:$B$17,MATCH(F64,Weights!$A$5:$A$17,0)),0) -> 2 | P64: =IFERROR(INDEX(Weights!$B$21:$B$23,MATCH(I64,Weights!$A$21:$A$23,0)),0) -> 0.7 | Q64: =IF(L64<>"",IFERROR(INDEX(Weights!$B$33:$B$36,MATCH(L64,Weights!$A$33:$A$36,0)),0),IFERROR(INDEX(Weights!$B$27:$B$29,MATCH(K64,Weights!$A$27:$A$29,0)),0)) -> 0.25 | R64: =N64*O64*P64*Q64 -> 0.35
A65: ST64 | B65: 2026 | C65: Event organiser | D65: JornadaID | E65: 351 helped with first contacts for a women-focused founder event | F65: L | G65: Ecosystem Enablement | H65: N | I65: C | J65: Team account | K65: Contributing | N65: =IF(OR(M65<>"",F65="X",F65="O",F65="Q"),0,1) -> 1 | O65: =IFERROR(INDEX(Weights!$B$5:$B$17,MATCH(F65,Weights!$A$5:$A$17,0)),0) -> 2 | P65: =IFERROR(INDEX(Weights!$B$21:$B$23,MATCH(I65,Weights!$A$21:$A$23,0)),0) -> 0.4 | Q65: =IF(L65<>"",IFERROR(INDEX(Weights!$B$33:$B$36,MATCH(L65,Weights!$A$33:$A$36,0)),0),IFERROR(INDEX(Weights!$B$27:$B$29,MATCH(K65,Weights!$A$27:$A$29,0)),0)) -> 0.25 | R65: =N65*O65*P65*Q65 -> 0.2 | S65: Check Community Fund link
A66: ST65 | B66: 2026 | C66: 351 team member | D66: Ecosystem award | E66: Ecosystem award 2026 | F66: X | G66: Ecosystem Enablement | H66: Y | I66: C | J66: Team account | K66: Unclear | N66: =IF(OR(M66<>"",F66="X",F66="O",F66="Q"),0,1) -> 0 | O66: =IFERROR(INDEX(Weights!$B$5:$B$17,MATCH(F66,Weights!$A$5:$A$17,0)),0) -> 0 | P66: =IFERROR(INDEX(Weights!$B$21:$B$23,MATCH(I66,Weights!$A$21:$A$23,0)),0) -> 0.4 | Q66: =IF(L66<>"",IFERROR(INDEX(Weights!$B$33:$B$36,MATCH(L66,Weights!$A$33:$A$36,0)),0),IFERROR(INDEX(Weights!$B$27:$B$29,MATCH(K66,Weights!$A$27:$A$29,0)),0)) -> 0.1 | R66: =N66*O66*P66*Q66 -> 0 | S66: Report as credibility
A67: ST66 | B67: 2024/2025 | C67: Coworking Thursdays volunteer | D67: Coworking Thursdays (volunteer) | E67: Heard of an Impact Hub job through CT, applied and was hired; freelances for a 351 member | F67: J | G67: Community Building | H67: N | I67: C | J67: Team account | K67: Direct | N67: =IF(OR(M67<>"",F67="X",F67="O",F67="Q"),0,1) -> 1 | O67: =IFERROR(INDEX(Weights!$B$5:$B$17,MATCH(F67,Weights!$A$5:$A$17,0)),0) -> 2 | P67: =IFERROR(INDEX(Weights!$B$21:$B$23,MATCH(I67,Weights!$A$21:$A$23,0)),0) -> 0.4 | Q67: =IF(L67<>"",IFERROR(INDEX(Weights!$B$33:$B$36,MATCH(L67,Weights!$A$33:$A$36,0)),0),IFERROR(INDEX(Weights!$B$27:$B$29,MATCH(K67,Weights!$A$27:$A$29,0)),0)) -> 0.5 | R67: =N67*O67*P67*Q67 -> 0.4
A68: GP01 | C68: Weekend participant (SW Coimbra) | D68: Startup Weekend Coimbra | E68: Secured a partnership with a key organisation | F68: N | G68: Ideation | H68: N | I68: B | J68: LinkedIn post | K68: Contributing | N68: =IF(OR(M68<>"",F68="X",F68="O",F68="Q"),0,1) -> 1 | O68: =IFERROR(INDEX(Weights!$B$5:$B$17,MATCH(F68,Weights!$A$5:$A$17,0)),0) -> 1.5 | P68: =IFERROR(INDEX(Weights!$B$21:$B$23,MATCH(I68,Weights!$A$21:$A$23,0)),0) -> 0.7 | Q68: =IF(L68<>"",IFERROR(INDEX(Weights!$B$33:$B$36,MATCH(L68,Weights!$A$33:$A$36,0)),0),IFERROR(INDEX(Weights!$B$27:$B$29,MATCH(K68,Weights!$A$27:$A$29,0)),0)) -> 0.25 | R68: =N68*O68*P68*Q68 -> 0.2625 | S68: Name the partner
A69: GP02 | C69: FI participant | D69: Founder Institute | E69: "Best meetup I've been to" in 6 months | F69: V | G69: Company Creation | H69: N | I69: B | J69: Her LinkedIn post | K69: Direct | N69: =IF(OR(M69<>"",F69="X",F69="O",F69="Q"),0,1) -> 1 | O69: =IFERROR(INDEX(Weights!$B$5:$B$17,MATCH(F69,Weights!$A$5:$A$17,0)),0) -> 0.25 | P69: =IFERROR(INDEX(Weights!$B$21:$B$23,MATCH(I69,Weights!$A$21:$A$23,0)),0) -> 0.7 | Q69: =IF(L69<>"",IFERROR(INDEX(Weights!$B$33:$B$36,MATCH(L69,Weights!$A$33:$A$36,0)),0),IFERROR(INDEX(Weights!$B$27:$B$29,MATCH(K69,Weights!$A$27:$A$29,0)),0)) -> 0.5 | R69: =N69*O69*P69*Q69 -> 0.0875
A70: GP03 | C70: Coworking Thursdays member | D70: Coworking Thursdays | E70: Free SIMCONF ticket | F70: O | G70: Community Building | H70: N | I70: B | J70: His LinkedIn post | K70: Direct | N70: =IF(OR(M70<>"",F70="X",F70="O",F70="Q"),0,1) -> 0 | O70: =IFERROR(INDEX(Weights!$B$5:$B$17,MATCH(F70,Weights!$A$5:$A$17,0)),0) -> 0 | P70: =IFERROR(INDEX(Weights!$B$21:$B$23,MATCH(I70,Weights!$A$21:$A$23,0)),0) -> 0.7 | Q70: =IF(L70<>"",IFERROR(INDEX(Weights!$B$33:$B$36,MATCH(L70,Weights!$A$33:$A$36,0)),0),IFERROR(INDEX(Weights!$B$27:$B$29,MATCH(K70,Weights!$A$27:$A$29,0)),0)) -> 0.5 | R70: =N70*O70*P70*Q70 -> 0 | S70: Benefit, not outcome
A71: GP04 | C71: Weekend founder (SW Évora) | D71: Startup Weekend Évora | E71: Incubated at Fundação Eugénio de Almeida + Founder Institute scholarship | F71: S2 | G71: Company Creation | H71: N | I71: A | J71: PRR evidence file + his LinkedIn | K71: Direct | M71: ST29 | N71: =IF(OR(M71<>"",F71="X",F71="O",F71="Q"),0,1) -> 0 | O71: =IFERROR(INDEX(Weights!$B$5:$B$17,MATCH(F71,Weights!$A$5:$A$17,0)),0) -> 2 | P71: =IFERROR(INDEX(Weights!$B$21:$B$23,MATCH(I71,Weights!$A$21:$A$23,0)),0) -> 1 | Q71: =IF(L71<>"",IFERROR(INDEX(Weights!$B$33:$B$36,MATCH(L71,Weights!$A$33:$A$36,0)),0),IFERROR(INDEX(Weights!$B$27:$B$29,MATCH(K71,Weights!$A$27:$A$29,0)),0)) -> 0.5 | R71: =N71*O71*P71*Q71 -> 0 | S71: Part of ST29 + adds FI scholarship
A72: GP05 | C72: Startup Weekend participants | D72: Startup Weekends | E72: "Best weekend of my life" feedback | F72: V | G72: Ideation | H72: N | I72: A | J72: SW feedback sheet | K72: Direct | N72: =IF(OR(M72<>"",F72="X",F72="O",F72="Q"),0,1) -> 1 | O72: =IFERROR(INDEX(Weights!$B$5:$B$17,MATCH(F72,Weights!$A$5:$A$17,0)),0) -> 0.25 | P72: =IFERROR(INDEX(Weights!$B$21:$B$23,MATCH(I72,Weights!$A$21:$A$23,0)),0) -> 1 | Q72: =IF(L72<>"",IFERROR(INDEX(Weights!$B$33:$B$36,MATCH(L72,Weights!$A$33:$A$36,0)),0),IFERROR(INDEX(Weights!$B$27:$B$29,MATCH(K72,Weights!$A$27:$A$29,0)),0)) -> 0.5 | R72: =N72*O72*P72*Q72 -> 0.125 | S72: Count share of 9-10 scores
A73: GP06 | C73: Weekend founder (SW Évora) | D73: Startup Weekend Évora | E73: Incubated at Fundação Eugénio de Almeida | F73: S2 | G73: Company Creation | H73: N | I73: B | J73: His LinkedIn post | K73: Direct | M73: ST29 | N73: =IF(OR(M73<>"",F73="X",F73="O",F73="Q"),0,1) -> 0 | O73: =IFERROR(INDEX(Weights!$B$5:$B$17,MATCH(F73,Weights!$A$5:$A$17,0)),0) -> 2 | P73: =IFERROR(INDEX(Weights!$B$21:$B$23,MATCH(I73,Weights!$A$21:$A$23,0)),0) -> 0.7 | Q73: =IF(L73<>"",IFERROR(INDEX(Weights!$B$33:$B$36,MATCH(L73,Weights!$A$33:$A$36,0)),0),IFERROR(INDEX(Weights!$B$27:$B$29,MATCH(K73,Weights!$A$27:$A$29,0)),0)) -> 0.5 | R73: =N73*O73*P73*Q73 -> 0 | S73: Part of ST29
A74: GP07 | C74: Weekend participant | D74: Startup Weekend Coimbra | E74: No text in sheet | F74: Q | G74: Ideation | H74: N | I74: C | J74: Link only | K74: Unclear | N74: =IF(OR(M74<>"",F74="X",F74="O",F74="Q"),0,1) -> 0 | O74: =IFERROR(INDEX(Weights!$B$5:$B$17,MATCH(F74,Weights!$A$5:$A$17,0)),0) -> 0 | P74: =IFERROR(INDEX(Weights!$B$21:$B$23,MATCH(I74,Weights!$A$21:$A$23,0)),0) -> 0.4 | Q74: =IF(L74<>"",IFERROR(INDEX(Weights!$B$33:$B$36,MATCH(L74,Weights!$A$33:$A$36,0)),0),IFERROR(INDEX(Weights!$B$27:$B$29,MATCH(K74,Weights!$A$27:$A$29,0)),0)) -> 0.1 | R74: =N74*O74*P74*Q74 -> 0 | S74: Add what changed
A75: GP08 | C75: Weekend participant | D75: Startup Weekend Albufeira | E75: LinkedIn post, no text in sheet | F75: Q | G75: Ideation | H75: N | I75: B | J75: Her LinkedIn post | K75: Unclear | N75: =IF(OR(M75<>"",F75="X",F75="O",F75="Q"),0,1) -> 0 | O75: =IFERROR(INDEX(Weights!$B$5:$B$17,MATCH(F75,Weights!$A$5:$A$17,0)),0) -> 0 | P75: =IFERROR(INDEX(Weights!$B$21:$B$23,MATCH(I75,Weights!$A$21:$A$23,0)),0) -> 0.7 | Q75: =IF(L75<>"",IFERROR(INDEX(Weights!$B$33:$B$36,MATCH(L75,Weights!$A$33:$A$36,0)),0),IFERROR(INDEX(Weights!$B$27:$B$29,MATCH(K75,Weights!$A$27:$A$29,0)),0)) -> 0.1 | R75: =N75*O75*P75*Q75 -> 0 | S75: Add what changed
A76: GP09 | C76: Weekend founder | D76: Startup Weekend Albufeira | E76: Two weeks after SW, kept going: Startuppers 2025 + 2026 | F76: S2 | G76: Company Creation | H76: N | I76: A | J76: PRR evidence file + her LinkedIn | K76: Direct | N76: =IF(OR(M76<>"",F76="X",F76="O",F76="Q"),0,1) -> 1 | O76: =IFERROR(INDEX(Weights!$B$5:$B$17,MATCH(F76,Weights!$A$5:$A$17,0)),0) -> 2 | P76: =IFERROR(INDEX(Weights!$B$21:$B$23,MATCH(I76,Weights!$A$21:$A$23,0)),0) -> 1 | Q76: =IF(L76<>"",IFERROR(INDEX(Weights!$B$33:$B$36,MATCH(L76,Weights!$A$33:$A$36,0)),0),IFERROR(INDEX(Weights!$B$27:$B$29,MATCH(K76,Weights!$A$27:$A$29,0)),0)) -> 0.5 | R76: =N76*O76*P76*Q76 -> 1
A77: GP10 | C77: 351 team member | D77: Policy (DMA) | E77: 351 warned about suspending the Digital Markets Act in national press | F77: X | G77: Ecosystem Enablement | H77: Y | I77: A | J77: Press: PME Magazine | K77: Direct | N77: =IF(OR(M77<>"",F77="X",F77="O",F77="Q"),0,1) -> 0 | O77: =IFERROR(INDEX(Weights!$B$5:$B$17,MATCH(F77,Weights!$A$5:$A$17,0)),0) -> 0 | P77: =IFERROR(INDEX(Weights!$B$21:$B$23,MATCH(I77,Weights!$A$21:$A$23,0)),0) -> 1 | Q77: =IF(L77<>"",IFERROR(INDEX(Weights!$B$33:$B$36,MATCH(L77,Weights!$A$33:$A$36,0)),0),IFERROR(INDEX(Weights!$B$27:$B$29,MATCH(K77,Weights!$A$27:$A$29,0)),0)) -> 0.5 | R77: =N77*O77*P77*Q77 -> 0 | S77: Move to policy log
A78: GP11 | C78: Coworking Thursdays member | D78: Coworking Thursdays Porto & Lisboa | E78: LinkedIn post about CT | F78: V | G78: Community Building | H78: N | I78: B | J78: Her LinkedIn post | K78: Direct | N78: =IF(OR(M78<>"",F78="X",F78="O",F78="Q"),0,1) -> 1 | O78: =IFERROR(INDEX(Weights!$B$5:$B$17,MATCH(F78,Weights!$A$5:$A$17,0)),0) -> 0.25 | P78: =IFERROR(INDEX(Weights!$B$21:$B$23,MATCH(I78,Weights!$A$21:$A$23,0)),0) -> 0.7 | Q78: =IF(L78<>"",IFERROR(INDEX(Weights!$B$33:$B$36,MATCH(L78,Weights!$A$33:$A$36,0)),0),IFERROR(INDEX(Weights!$B$27:$B$29,MATCH(K78,Weights!$A$27:$A$29,0)),0)) -> 0.5 | R78: =N78*O78*P78*Q78 -> 0.0875
A79: GP12 | C79: 351 team member | D79: Volunteering | E79: Forbes Portugal 30 Under 30 | F79: X | G79: Ecosystem Enablement | H79: Y | I79: B | J79: Her LinkedIn post | K79: Unclear | N79: =IF(OR(M79<>"",F79="X",F79="O",F79="Q"),0,1) -> 0 | O79: =IFERROR(INDEX(Weights!$B$5:$B$17,MATCH(F79,Weights!$A$5:$A$17,0)),0) -> 0 | P79: =IFERROR(INDEX(Weights!$B$21:$B$23,MATCH(I79,Weights!$A$21:$A$23,0)),0) -> 0.7 | Q79: =IF(L79<>"",IFERROR(INDEX(Weights!$B$33:$B$36,MATCH(L79,Weights!$A$33:$A$36,0)),0),IFERROR(INDEX(Weights!$B$27:$B$29,MATCH(K79,Weights!$A$27:$A$29,0)),0)) -> 0.1 | R79: =N79*O79*P79*Q79 -> 0 | S79: Report as credibility
A80: GP13 | C80: Coworking Thursdays member | D80: Coworking Thursdays Porto | E80: "Didn't know what to expect" — positive post on CT Porto | F80: V | G80: Community Building | H80: N | I80: B | J80: His LinkedIn post | K80: Direct | N80: =IF(OR(M80<>"",F80="X",F80="O",F80="Q"),0,1) -> 1 | O80: =IFERROR(INDEX(Weights!$B$5:$B$17,MATCH(F80,Weights!$A$5:$A$17,0)),0) -> 0.25 | P80: =IFERROR(INDEX(Weights!$B$21:$B$23,MATCH(I80,Weights!$A$21:$A$23,0)),0) -> 0.7 | Q80: =IF(L80<>"",IFERROR(INDEX(Weights!$B$33:$B$36,MATCH(L80,Weights!$A$33:$A$36,0)),0),IFERROR(INDEX(Weights!$B$27:$B$29,MATCH(K80,Weights!$A$27:$A$29,0)),0)) -> 0.5 | R80: =N80*O80*P80*Q80 -> 0.0875
A81: GP14 | C81: Coworking Thursdays volunteer | D81: Coworking Thursdays Porto (volunteer) | E81: Became a CT Porto volunteer | F81: L | G81: Community Building | H81: N | I81: B | J81: His LinkedIn posts | K81: Direct | N81: =IF(OR(M81<>"",F81="X",F81="O",F81="Q"),0,1) -> 1 | O81: =IFERROR(INDEX(Weights!$B$5:$B$17,MATCH(F81,Weights!$A$5:$A$17,0)),0) -> 2 | P81: =IFERROR(INDEX(Weights!$B$21:$B$23,MATCH(I81,Weights!$A$21:$A$23,0)),0) -> 0.7 | Q81: =IF(L81<>"",IFERROR(INDEX(Weights!$B$33:$B$36,MATCH(L81,Weights!$A$33:$A$36,0)),0),IFERROR(INDEX(Weights!$B$27:$B$29,MATCH(K81,Weights!$A$27:$A$29,0)),0)) -> 0.5 | R81: =N81*O81*P81*Q81 -> 0.7
A82: GP15 | C82: Coworking Thursdays member | D82: Coworking Thursdays Porto | E82: "Networking that feels good" post | F82: V | G82: Community Building | H82: N | I82: B | J82: Her LinkedIn post | K82: Direct | N82: =IF(OR(M82<>"",F82="X",F82="O",F82="Q"),0,1) -> 1 | O82: =IFERROR(INDEX(Weights!$B$5:$B$17,MATCH(F82,Weights!$A$5:$A$17,0)),0) -> 0.25 | P82: =IFERROR(INDEX(Weights!$B$21:$B$23,MATCH(I82,Weights!$A$21:$A$23,0)),0) -> 0.7 | Q82: =IF(L82<>"",IFERROR(INDEX(Weights!$B$33:$B$36,MATCH(L82,Weights!$A$33:$A$36,0)),0),IFERROR(INDEX(Weights!$B$27:$B$29,MATCH(K82,Weights!$A$27:$A$29,0)),0)) -> 0.5 | R82: =N82*O82*P82*Q82 -> 0.0875
A83: GP16 | C83: 351 team member | D83: Team | E83: Sifted top 100 women in tech | F83: X | G83: Ecosystem Enablement | H83: Y | I83: B | J83: Her LinkedIn post | K83: Unclear | N83: =IF(OR(M83<>"",F83="X",F83="O",F83="Q"),0,1) -> 0 | O83: =IFERROR(INDEX(Weights!$B$5:$B$17,MATCH(F83,Weights!$A$5:$A$17,0)),0) -> 0 | P83: =IFERROR(INDEX(Weights!$B$21:$B$23,MATCH(I83,Weights!$A$21:$A$23,0)),0) -> 0.7 | Q83: =IF(L83<>"",IFERROR(INDEX(Weights!$B$33:$B$36,MATCH(L83,Weights!$A$33:$A$36,0)),0),IFERROR(INDEX(Weights!$B$27:$B$29,MATCH(K83,Weights!$A$27:$A$29,0)),0)) -> 0.1 | R83: =N83*O83*P83*Q83 -> 0 | S83: Report as credibility
A84: GP17 | C84: 351 (organisation) | D84: Team | E84: Sifted: 50 best first-time founder communities in Europe 2025 | F84: X | G84: Community Building | H84: Y | I84: A | J84: Sifted LinkedIn post | K84: Direct | N84: =IF(OR(M84<>"",F84="X",F84="O",F84="Q"),0,1) -> 0 | O84: =IFERROR(INDEX(Weights!$B$5:$B$17,MATCH(F84,Weights!$A$5:$A$17,0)),0) -> 0 | P84: =IFERROR(INDEX(Weights!$B$21:$B$23,MATCH(I84,Weights!$A$21:$A$23,0)),0) -> 1 | Q84: =IF(L84<>"",IFERROR(INDEX(Weights!$B$33:$B$36,MATCH(L84,Weights!$A$33:$A$36,0)),0),IFERROR(INDEX(Weights!$B$27:$B$29,MATCH(K84,Weights!$A$27:$A$29,0)),0)) -> 0.5 | R84: =N84*O84*P84*Q84 -> 0 | S84: Report as credibility
A85: GP18 | C85: Community member | D85: Several 351 initiatives | E85: Connected with the Lisbon ecosystem | F85: V | G85: Community Building | H85: N | I85: C | J85: No link | K85: Contributing | N85: =IF(OR(M85<>"",F85="X",F85="O",F85="Q"),0,1) -> 1 | O85: =IFERROR(INDEX(Weights!$B$5:$B$17,MATCH(F85,Weights!$A$5:$A$17,0)),0) -> 0.25 | P85: =IFERROR(INDEX(Weights!$B$21:$B$23,MATCH(I85,Weights!$A$21:$A$23,0)),0) -> 0.4 | Q85: =IF(L85<>"",IFERROR(INDEX(Weights!$B$33:$B$36,MATCH(L85,Weights!$A$33:$A$36,0)),0),IFERROR(INDEX(Weights!$B$27:$B$29,MATCH(K85,Weights!$A$27:$A$29,0)),0)) -> 0.25 | R85: =N85*O85*P85*Q85 -> 0.025 | S85: Add link
A86: GP19 | C86: Volunteer | D86: Several 351 initiatives | E86: Her top LinkedIn connections of the year all came from 351 | F86: V | G86: Community Building | H86: N | I86: B | J86: Her LinkedIn post | K86: Direct | M86: ST62 | N86: =IF(OR(M86<>"",F86="X",F86="O",F86="Q"),0,1) -> 0 | O86: =IFERROR(INDEX(Weights!$B$5:$B$17,MATCH(F86,Weights!$A$5:$A$17,0)),0) -> 0.25 | P86: =IFERROR(INDEX(Weights!$B$21:$B$23,MATCH(I86,Weights!$A$21:$A$23,0)),0) -> 0.7 | Q86: =IF(L86<>"",IFERROR(INDEX(Weights!$B$33:$B$36,MATCH(L86,Weights!$A$33:$A$36,0)),0),IFERROR(INDEX(Weights!$B$27:$B$29,MATCH(K86,Weights!$A$27:$A$29,0)),0)) -> 0.5 | R86: =N86*O86*P86*Q86 -> 0 | S86: Same person as ST62 (different outcome kept as felt value)
A87: GP20 | C87: FI participant | D87: Founder Institute | E87: Access to SIMCONF | F87: O | G87: Company Creation | H87: N | I87: B | J87: Her LinkedIn post | K87: Direct | N87: =IF(OR(M87<>"",F87="X",F87="O",F87="Q"),0,1) -> 0 | O87: =IFERROR(INDEX(Weights!$B$5:$B$17,MATCH(F87,Weights!$A$5:$A$17,0)),0) -> 0 | P87: =IFERROR(INDEX(Weights!$B$21:$B$23,MATCH(I87,Weights!$A$21:$A$23,0)),0) -> 0.7 | Q87: =IF(L87<>"",IFERROR(INDEX(Weights!$B$33:$B$36,MATCH(L87,Weights!$A$33:$A$36,0)),0),IFERROR(INDEX(Weights!$B$27:$B$29,MATCH(K87,Weights!$A$27:$A$29,0)),0)) -> 0.5 | R87: =N87*O87*P87*Q87 -> 0 | S87: Benefit, not outcome
A88: GP21 | B88: 2026 | C88: FI demo day guest | D88: Founder Institute Demo Day | E88: Praised the FI demo day event | F88: V | G88: Company Creation | H88: N | I88: B | J88: Her LinkedIn post | K88: Direct | N88: =IF(OR(M88<>"",F88="X",F88="O",F88="Q"),0,1) -> 1 | O88: =IFERROR(INDEX(Weights!$B$5:$B$17,MATCH(F88,Weights!$A$5:$A$17,0)),0) -> 0.25 | P88: =IFERROR(INDEX(Weights!$B$21:$B$23,MATCH(I88,Weights!$A$21:$A$23,0)),0) -> 0.7 | Q88: =IF(L88<>"",IFERROR(INDEX(Weights!$B$33:$B$36,MATCH(L88,Weights!$A$33:$A$36,0)),0),IFERROR(INDEX(Weights!$B$27:$B$29,MATCH(K88,Weights!$A$27:$A$29,0)),0)) -> 0.5 | R88: =N88*O88*P88*Q88 -> 0.0875

Sheet Records
A1: ID | B1: Outcome code | C1: What | D1: Count | E1: Evidence grade | F1: Source | G1: 351 role | H1: Outcome weight | I1: Evidence weight | J1: 351 share | K1: Impact points (Founder Steps)
A2: REC-S1 | B2: S1 | C2: Startups created at Techstars Startup Weekends (Porto, Lisboa, Coimbra, Albufeira, Évora, Viseu), Oct 2024–Oct 2025 | D2: 47 | E2: A | F2: PRR 5196 evidence file, tab "Startups constituídas" (47 named) | G2: Direct | H2: =IFERROR(INDEX(Weights!$B$5:$B$17,MATCH(B2,Weights!$A$5:$A$17,0)),0) -> 1 | I2: =IFERROR(INDEX(Weights!$B$21:$B$23,MATCH(E2,Weights!$A$21:$A$23,0)),0) -> 1 | J2: =IFERROR(INDEX(Weights!$B$27:$B$29,MATCH(G2,Weights!$A$27:$A$29,0)),0) -> 0.5 | K2: =D2*H2*I2*J2 -> 23.5
A3: REC-C | B3: C | C3: Weekend participants who came back to another 351 programme (73 of 225 = 32%) | D3: 73 | E3: A | F3: PRR 5196 evidence file, tab "Continuidade do apoio" (73 named) | G3: Direct | H3: =IFERROR(INDEX(Weights!$B$5:$B$17,MATCH(B3,Weights!$A$5:$A$17,0)),0) -> 0.5 | I3: =IFERROR(INDEX(Weights!$B$21:$B$23,MATCH(E3,Weights!$A$21:$A$23,0)),0) -> 1 | J3: =IFERROR(INDEX(Weights!$B$27:$B$29,MATCH(G3,Weights!$A$27:$A$29,0)),0) -> 0.5 | K3: =D3*H3*I3*J3 -> 18.25
A4: REC-L | B4: L | C4: CLA 2025 working groups (Talent, Culture, Density, Capital, Regulation) still active after the programme | D4: 5 | E4: C | F4: PRR impact report (team statement, no record yet) | G4: Direct | H4: =IFERROR(INDEX(Weights!$B$5:$B$17,MATCH(B4,Weights!$A$5:$A$17,0)),0) -> 2 | I4: =IFERROR(INDEX(Weights!$B$21:$B$23,MATCH(E4,Weights!$A$21:$A$23,0)),0) -> 0.4 | J4: =IFERROR(INDEX(Weights!$B$27:$B$29,MATCH(G4,Weights!$A$27:$A$29,0)),0) -> 0.5 | K4: =D4*H4*I4*J4 -> 2
A7: Not counted as outcomes (outputs / reach, kept for context):
C8: Startuppers 2025 participants with 3+ sessions (PRR file says 72; it includes 351's own programs@ account) | D8: 71
C9: Distinct startups that received partner perks (all time) | D9: 163
C10: New 351 community members Feb 2024–Dec 2025 | D10: 643
C11: Community leaders trained at CLA (2 editions) | D11: 75
C12: Mentors mobilised at Weekends | D12: 46
C14: Story rows coded S1 for Weekend startups are marked "Duplicate of REC-S1" so they are not counted twice.

Sheet Survey
A1: Follow-up survey to past participants (5 questions, ~3 minutes)
A3: # | B3: Question | C3: Answer type | D3: Feeds
A4: 1 | B4: Which 351 activities did you take part in? (Startup Weekend, Coworking Thursdays, Startuppers, Founder Institute, CLA, PTW, Slack, volunteering, other) | C4: Multiple choice | D4: Initiative, funnel stage
A5: 2 | B5: Since then, what happened? Tick all that apply: started a company · joined an incubator/accelerator · launched a product · first paying client · raised funding (amount optional) · won an award · got a job or new role · found a co-founder, partner, client or hire · started a community or event · none yet | C5: Multiple choice + amount | D5: Outcome codes S1–S4, J, N, L
A6: 3 | B6: Pick the most important of these. In one or two sentences, what was 351's part in it? | C6: Short text | D6: What changed, 351 role
A7: 4 | B7: Would this have happened without 351? No, definitely not · Probably not · Yes, but later or smaller · Yes, the same anyway | C7: Single choice | D7: 351 share (counterfactual)
A8: 5 | B8: Can we quote you and use your name? Yes, with name · Yes, anonymous · No. Optional: link to a post or page that shows it | C8: Single choice + link | D8: Evidence grade (B, or A with an independent link)
A10: Send to: Startup Weekend participants (225), Startuppers 2025 (199), Founder Institute cohorts, CLA leaders (75), volunteers. Send in Portuguese and English. Two reminders, one week apart.
